{
  "document": {
    "id": "efta00010724",
    "filename": "EFTA00010724.pdf",
    "path": "C:\\Users\\user\\CascadeProjects\\epsteinexposed\\apps\\web\\DataSet 8\\VOL00008\\IMAGES\\0001\\EFTA00010724.pdf",
    "text": "\n\nFrom: Chris \nDilorio \nTo: \nSubject: Fw: Apollo/ Epstein/Kushner \nconnection \nDate: Thu, 18 Jul 2019 17:54:54 +0000 \nAttachments: IMG_7021.jpg \nInline-Images: image.png \nHealthcare fraud is pretty serious shit. \nWhat SECURITIES LAWS should be \nhttps://www.law.cornell.edu/uscode/text/18/1347 \n18 U.S. Code § 1347 \n- Health care fraud I U.S. \nCode I US Law \nI \n0 \n/ Legal Information \nInstitute \nto obtain, by means of false or fraudulent pretenses, \nrepresentations, or promises, any of the money or property \nowned by, or under the custody or control of, any health care \nbenefit program, \nwww.law.cornell.edu \nEFTA00010724\n\nColleran got off pretty easy, eh? \nCertainly LOOKS like CRIMINAL fraud and \nNOT \nCIVIL fraud \nTrump: \n'acting' Asst DOJ Readier becomes JUDGE Readier just like that \nhttps://en.wikipedia.org/wiki/Chad \nReadier \nChad Readler - Wikipedia \nAugust 23, 1972 (age 46) Pontiac, Michigan, U.S.: Education: \nUniversity of Michigan (BA, JD): Chad Andrew Readler (born \nAugust 23, 1972) is a United States Circuit Judge of the United \nStates Court of Appeals for the Sixth Circuit and former Principal \nDeputy and former Acting Assistant Attorney General for the \nen.wikipedia.org \nThe criminality associated with this White House is off the charts. \nCalk: Lorber \nLorber/Elliman/lcahn: Frost/Honig/Stetson \nAND \nAlpha Capital: Martin Schlaff: MY CLAIMS \nLadenburg/Gruntal: Refco/Bawag \nAlso Schlaff AND: Englander/Nordlicht/Kushners \nabusive naked shorting to facilitate $$ laundering: Sedona/ Scan Graphics \nMy claims: NITE/VIRT: Refco on steroids \nalso CDEL \nFrost brings down the WH \nFrost/Honig/Stetson: Therapix/FSDDF \nUrban: FSDDF/NITE/VIRT \nBlackstone: Luckiest fuckers on the Street: Here glitchy glitchy \nEpstein: Schwarzman \nEpstein: Black \nBlack/Schwarzman: Kushner (my BX SEC TCR) \nSEC: dropped Apollo charges: Avakian/Heiss \nSEC NITE/VIRT obstruction: Jay/Sull Crom/Fishman \n1MDB: PHUN/Nordlicht/AIPAC: Greek shippers \nEconomou/EKONOMOU \nBistricers \nFeinberg: Danaos \nTrump attorney: EKONOMOU \nBarr 1MDB waiver: AQR \nCheers! \nFollow me on Twitter \nI'll follow back \nIololol \nEFTA00010725\n\nFrom: Chris Dilorio \nSent: Saturday, July 13, 2019 7:31 AM \nTo: \nSubject: Fw: Apollo/ Epstein/Kushner connection \nMore.... \nTrump Ohio fundraiser \nBrian Colleran \nhttps://www.cleveland.com/politics/2019/07/donald-trump-com \ning-to-cleveland-f riday-for-fundraiser-at-\nnursing-home-magnates-house.html \nDonald Trump coming to Cleveland Friday for \nfundraiser at nursing home magnate's house - \ncleveland.com \nCLEVELAND, Ohio —  Republican President Donald Trump is \nvisiting Cleveland on Friday for a private fundraiser at the home \nof nursing home executive Brian Colleran, sources with \nknowledge of the ... \nwww.cleveland.com \nhttps://www.justice gov/opa/pethree-companies-and-their-executives-pay-195-million-resolve-false-claims-act-\nallegations \nEFTA00010726\n\nThree Companies and Their Executives Pay $19.5 \nMillion to Resolve False Claims Act Allegations \nPertaining to Rehabilitation Therapy and Hospice \nServices I OPA I Department of Justice \nOhio based Foundations Health Solutions Inc. (FHS), Olympia Therapy Inc. \n(Olympia), and India Hospice Care Inc. (Tridia), and their executives, Brian \nColleran (Colleran) and Daniel Parker (Parker), have agreed to pay \napproximately $19.5 million to resolve allegations pertaining to the submission \nof false claims for medically unnecessary rehabilitation therapy and hospice \nwwwjustice.gov \nAnother Honig $$$ laundering shell \nIntergetics \nMillenium \nNMC \nRegent \ntake your pick \nhttps://www.sec.gov/cgi-bin/browse-edgar? \naction=getcompany&CIK=0000072170&owner=exclude&count=40&hidefilings=0 \nhttpsliwww sec  gov/Archives/edgar/data/72170/000114420410011488/0001144204-10-011488-index.htm \nColleran \nhttps://www.sec.gov/Archives/edgar/data/72170/000114420408023159/0001144204-08-023159-index.htm \nCheers! \nChristopher Dilorio \nand \nFrom: Chris Dilorio \nSent: Thursday, July 11, 2019 8:07 AM \nTo: \n< \nEFTA00010727\n\nSubject: Fw: Apollo/ Epstein/Kushner connection \nMr Berman, \nThanks for the shout out, but I'm not a journalist \nlololol \nJust a very long list of credible information I have provided to the grossly corrupt SEC et al scumbags \nJaney, update my various TCR's and derivatives. Separate but related Janey. Separate but related. \nHey, is Jay still working on his NITE/VIRT/Sull Crom disclosures? \nhttps://www.nyti \nmes.com/2019/07/10/business/jeffrey-epstein-net-worth.html \nJeffrey Epstein's 'Infinite Means' May Be a Mirage \nMr. Epstein, facing sex-trafficking charges, has long been hailed as a financial \nwizard. He got rich with the help of two wealthy connections, but there is little \nevidence he's a billionaire. \nwww.nytimes.com \nCheers! \nChristopher Dilorio \nFrom: Chris Dilorio \nSent: Monday, July 8, 2019 6:25 AM \nTo: \n< \nSubject: Fw: Apollo/ Epstein/Kushner connection \nGreetings Grossly corrupt SEC scumbags et al \nIMDS: S Florida $$$ laundering shell facilitated by the SEC \nHighlighted in my 2013 TCR filed with prestigious Berger Montague \nEFTA00010728\n\nMore AML flags than be counted \nMASSIVE naked short position \nMY claims \nSEC cover up. Now, re started so it can be unleashed on the investing public yet again. \nMartin Schlaff/Balmore/Alpha Cap \nhttps://www.haaretz.com/israel-news/business/martin-schlaff-is-behind-5-million-investment-in-collplant-\n1.5457018 \nMartin Schlaff: Bag Man \nBut it gets MUCH better \nGraftech \nSEC reporting \npronounced \"Graft etc\" \nhttps://www. sec.gov/Archives/edga r/data/931148/000119312516427770/0001193125-16-427770-i ndex. htm \nEDGAR Filing Documents for 0001193125-16-427770 \nGrafTech Global Enterprises Inc. (Filer) CIK: 0000940404 (see all company filings) IRS No.: 061415602 I State \nof Incorp.:DE I Fiscal Year End: 1231 Type: 15-15D I Act ... \nvAvw.sec.gov \nhttps://www.haaretz.com/israel-news/electionstpremium-the-netanyahu-milikowsky-ties-could-be-on-the-\nway-to-an-fbi-investigation-1.7090960 \nlei' \nThe FBI may be about to probe Netanyahu's \nties to cousin Milikowsky \nwww.haaretz.com \nWall Street / CNBC Wiz Karen Finerman \n\"Save Graft etc\" \nhttps://www.sec.gov/Archivesiedgar/data/931148/000119312515018174/d857124dex991.htm \nEX-99.1 - sec.gov \nExhibit 1 \"SAVE GRAFTECH\" GROUP NOMINATES FULL SLATE OF SEVEN DIRECTORS TO GRAFTECH BOARD \n. NEW YORK, January 23, 2015 -  Save GrafTech, an investor group led by Nathan Milikowsky, a holder of \nover 15 million shares, or over 11.2%, of the common stock of GrafTech International Ltd. (NYSE: GTI), today \nsent a letter to the GrafTech Board of Directors disclosing that it has submitted a ... \nvoNw.sec gov \nEFTA00010729\n\npg 57 of this SEC \nreviewed public offering \nhttps://vvvvw.sec.gov/Archives/edgar/data/931148/000104746919000874/a2237872zs-Lhtm \nwww.sec.gov \n(1) Includes 2,625,000 shares of common stock that the underwriters have the option to purchase from the \nselling stockholder (2) Estimated solely for the purpose of calculating the amount of registration fee in \naccordance with Rule 457(c) under the Securities Act of 1933, as amended, based upon the average of the \nhigh and low sales prices of the registrant's common stock as reported by the ... \nwww.sec.gov \n2018 revenue up 244% vs 2017 due to sharp increase in graphite electrode pricing \nBUT, graphite electrode prices rose significantly in 2017 \nand \nFELL in 2018 \nhttps://agmetalminer.corn/tag/graphite-electrodes/ \ngraphite electrodes Archives - Steel, Aluminum, Copper, \nStainless, Rare \nEarth, Metal Prices, Forecasting I MetalMiner \nNeedle coke, a crude oil derivative, accounts for 40-44% (depending on the year) of the cost to produce \none metric ton of electrodes. Graftech, one of the leaders in graphite electrode production ... \nagmetalminer.com \nthe Graftech/Graft etc balance sheet is complete fraud as well \ninsolvent \nJP Morgan strikes again \nGrossly corrupt SEC \"protecting Main Street as usual\" \nFraud certainly not limited to the \nOTCM \nMr Teotia, \ncongrats on taking Wes Bricker's job \nno doubt you're working hard on those KCG 2Q 2017 financials not \"published\" by Mr Transparency Dougie \nCifu. \nWhere would a $4 billion+ write down of naked short fails put the NITE/VIRT fraud on the list of egregious \nSEC \naccounting fraud failures? \nTop 5? \nLet me know if I can help \nIn furtherance of the conspiracy.... \nCheers! \nChristo her Ditorio \nFrom: Chris Dilorio < \nSent: Wednesday, June 26, 2019 6:07 AM \nTo: jd@johnnydwyermet; mmorrison@judicialwatch.org; jfarrell@judicialwatch.org \nSubject: Fw: Apollo/ Epstein/Kushner connection \nEFTA00010730\n\nFrom: Chris Dilorio \nSent: Tuesday, June 25, 2019 2:31 PM \nTo: \nSubject: Fw: Apollo/ Epstein/Kushner connection \nFrom: Chris Dilorio \nSent: Friday, May 24, 2019 7:27 AM \nTo: \nSubject: Fw: Apollo/ Epstein/Kushner connection \nFrom: Chris Dilorio \nSent: Friday, May 24, 2019 7:23 AM \nTo: \nSubject: Fw: Apollo/ Epstein/Kushner connection \nGetting warmer Ms Strauss \nhttgs://www.justice.gov/usao-sdnyigr/bank-ceo-stephen-m-calk-charged-corruptly-soliciting-presidential-\nadministration \nBank CEO Stephen M. Calk Charged With Corruptly \nSoliciting A Presidential Administration Position In \nExchange For Approving $16 Million In Loans I USAO-\nSDNY I Department of Justice \nAudrey Strauss, the Attorney for the United States, Acting Under Authority \nConferred by 28 U.S.C. §  515, William F.  Sweeney Jr, the Assistant Director-in-\nEFTA00010731\n\nCharge of the New York Field Office of the Federal Bureau of Investigation \n(\"FBI\"), and Patricia Tarasca, the Special Agent-in-Charge of the New York \nwwwjustice.gov \nBut, this is the beginning of the story \nnot the end \nCalk/Lorber/Elliman: Trump \nLorber: New Valley Corp \nhttps://www.sec.gov/Archives/edgar/data/106374/000095014405003084/g93826e10vk.htm \nApollo Moscow/Kremlin development \nAND \nLadenburg Thalman \nI asked in previous correspondence: \nDoes ANYONE believe Frost risked BILLIONS to \"MAKE\" a  few million? \nFrost was laundering a few millions. \nhttps://www.barrons.com/articles/sec-charges-phillip-frost-1536608366 \n;2, \nSEC Charges Against Phillip Frost Might Just \nBe the Tip of the Iceberg \nThe U.S. Securities and Exchange Commission filed stock fraud \ncharges late last week against billionaire drug entrepreneur Phillip \nFrost and a group of associates, accusing them of making $27 \nmillion in pump-and-dump stock schemes \nwww.barrons.com \nAlpha Capital Anstalt Liechtenstein \nin my 2013 TCR: Money laundering/Miami based Imaging Diagnostics (see my IMDS e mails) \nBag Men \nAlso: \"Greek Shipping company\" FreeSeas (See my FreeSeas TCR) \nDespite overwhelming evidence of money laundering, you will find no reference to it in SEC complaints. \nhttps://www.sec.gov/news/press-release/2018-182 \nSEC.gov I SEC Charges Microcap Fraudsters for Roles in Lucrative Market \nManipulation Schemes \nThe Securities and Exchange Commission today charged a group of 10 individuals and 10 associated \nentities for their participation in long-running fraudulent schemes that generated over $27 million from \nEFTA00010732\n\nunlawful stock sales and caused significant harm to retail investors who were left holding virtually worthless \nvo.vw.sec goy \nNo mention of AML despite glaring red flags \nNo mention of executing Broker Dealers: Penny stock trading fairies \nThe SEC has kept Alpha Capital Anstalt up and running so the activity detailed in my complaints can continue. \nAnd it does \nhttps://whalewisdom.com/filer/alpha-capital-anstalt \nALPHA CAPITAL ANSTALT Top Holdings - WhaleWisdom \nAlpha Capital Anstalt is based out of Vaduz Liechtenstein. Whalewisdom has at least 6 13D filings, 158 13G \nfilings, and 5 Form 4 filings The firm has no submitted 13F filings and does not appear to be an investment \nadvisor. \nwhalewisdom.com \nNow: Lorber/Calk/Elliman: New Valley: shell \nLadenburg/Frost/Alpha Cap Anstalt $$$ laundering shells \nApollo/Lorber: Moscow/Kremlin \"development\" \n\"Tip of the Iceberg\" indeed \nIn furtherance of the conspiracy \nCheers! \nChristopher Dilorio \nWhistleblower \nFrom: Chris Dilorio \nSent: Thursday, May 23, 2019 5:59 AM \nTo: \nSubject: Fw: Apollo/ Epstein/Kushner connection \nEFTA00010733\n\nSo: \nLeon Black/ Apollo/Schwarzman: Trump Kushner \nBlack/Apollo/Schwarzman: Epstein \nBlack/Apollo/Schwarzman: Putin/RU \nhttps://www.reuters.com/article/russia-putin-fund-idUSL5E7KG0SI20110916 \nUPDATE 2-Putin gets SWF, PE backing for \nRussia fund \n* Apollo's Black shares platform with Putin \nwww.reuters.com \nhttps://www.swfinstitute.org/news/33645/u-s-treasury-sanctions-russian-direct-investment-fund/amp\nBlack/Apollo/Schwarzman: money laundering shells \nhttps://www.businessinsider.com/blackstone-dodged-a-bullet-with-knight-capital-2012-8 \n;2. \nBlackstone Dodged A Bullet With Knight \nCapital - Business \nInsider \nA trader consulted by Business Insider said that Blackstone envied \nKnight Capital's market-making team, which executed an average \nof more than $20 billion trades last year and is designated market \nwww.businessinsider.com \nhttps://www.sec.gov/Archives/edgar/data/1082278/000092242313000183/0000922423-13-000183-index.htm \nICnight/Trimark/Optimark born out of \"worthless paper\"/ Russian/US Mafia/ money laundering shell: Ashton \nTechnologies \nhttps://www.sec.gov/cgi-bin/browse-edgar? \naction=getcompany&CIK=0001003740&owner=exclude&count=40&hidefilings=0 \nhttps://ag.ny.gov/press-release/us-attorney-lynch-and-nys-attomey-general-spitzer-announce-20-defendants-\nindicted-50 \nU.s. Attorney Lynch And N.y.s. Attorney General Spitzer Announce 20 \nDefendants Indicted In $50 Million Boiler Room Stock Fraud Scheme I New \nYork State \nAttorney General \nLORETTA E. LYNCH, United States Attorney for the Eastern District of New York, ELIOT SPITZER, New York \nState Attorney General, BARRY W. MAWN, Assistant Director-in-Charge of the Federal Bureau of \nEFTA00010734\n\nInvestigation in New York, and RICHARD H. WALKER, Director of the Division of Enforcement of the \nSecurities and Exchange Commission, today announced the unsealing of an indictment charging 20 ... \nag.ny.gov \nSpitzer taken down by RUSSIAN hooker \nhttps://nypost.com/20 1 6/02/ 1 6/spizter-accuser-a-young-jobless-ex-hooker-who-lives-a-life-of-luxury/ \nSpitzer accuser was a  $5K-a-night hooker \nwho lives life of luxury - New York Post \nThe Russian vixen who accused Eliot Spitzer of choking her at The \nPlaza hotel is a  divorced, globe-trotting beauty who once bared \nall the dirty details of her life as a $5,000-a-night hooker, The ... \nnypost.com \nAny questions? \nCheers traitorous scumbags! \nChristo her Dilorio \nFrom: Chris Dilorio \nSent: Sunday, May 19, 2019 8:03 AM \nTo: \nSubject: Fw: Apollo/ Epstein/Kushner connection \nI reiterate: \nThe SEC is a grossly corrupt criminal organization bought and paid for by criminals who threaten the integrity of \nour markets to the clear and very egregious detriment of the investing public it is sworn to protect. \nhttp://www.marketrap.com/article/view article/9152/bernard-madoff-the-mafia-and-the-friends-of-michael-\nmilken \nEFTA00010735\n\nBernard Madoff, the Mafia, and the Friends of Michael Milken - Market Rap \n- The Investor Empowerment Community \nIn 2005, Patrick Byrne, the CEO of Overstock.com and future Deep Capture investigative reporter, began a \npublic crusade against illegal naked short selling (hedge funds and brokers creating phantom stock to \nmanipulate stock prices down).He said, over and over, that the crime was destroying public companies and \nhad the potential to trigger a  systemic meltdown of our financial markets. \nwww.marketrap.com \nCheers! \nChristopher Dilorio \nFrom: Chris Dilorio \nc \nSent: Friday, May 17, 2019 6:22 AM \nTo: \nSubject: Fw: Apollo/ Epstein/Kushner connection \nFrom: Chris Dilorio \nSent: Wednesday, May 15, 2019 11:27 AM \nTo: \n< \nSubject: Fw: Apollo/ Epstein/Kushner connection \nToday (5/15/19) the grossly corrupt scumbags at the SEC approved ANOTHER massive fraud on the investing \npublic: \nhttps://www.sec.gov/Archives/edgar/data/1665300/999999999519001111/xsIEFFECTX01/primary doc.xml \nThe \"genius f'n quant\" AQR/Greek shipping \n/Economou/DRYWORIG/Astra/Nautilus/Navios/Gerber/AIPAC/Nordlicht/Glass/1MDB/Knitowski/Caneum/Trym \netris/Liquid etc etc etc money laundering shell. \nWell done! \nBTW, HOW is the George Economou/ Georgios EKONOMOU SEC \"investigation\" coming along anyway? \nhttps://en.wikipedia.org/wiki/George \nEconomou  (shipbuilder) \nEFTA00010736\n\nGeorge Economou (shipbuilder) - Wikipedia \nGeorge Economou or Georgios Ekonomou (Ildwytoc Otkovdμou, born 1953) is a Greek billionaire \nshipowner, CEO of DryShips Inc. and Ocean Rig, and the owner of Cardiff Marine.Economou owns oil \ntankers as well as dry bulk ships and manages them through Cardiff Marine. He was on the Forbes \nMagazines list of the world's billionaires on place 707. \nen.wikipedia.org \nWhat a coincidence: \nhttps://www.vanityfaiccominews/2018/03/andrew-ekonomou-donald-trump-legal-team  amp \nTrump's Last Line of Defense Against Mueller \nIs an Obscure \nMedieval Historian \nAndrew Ekonomou had a \"mid-life crisis\" and became an expert \non Byzantium. Now he's helping lead the president's legal team in \nthe Russia investigation. \nwww.vanityfair.com \nDude is DEFINITELY not getting the attention he deserves \nThen again, \nWHO actually believes Marc Bistricer of Toronto Canada was INVESTING in the US laundering Ekonomou \nshell known as DryShips? \nhttps://seekingalpha.com/article/4096781-strong-court-case-dryships-kalani\nVery Strong \nCourt Case Against DryShips And \nKalani - DryShips Inc. \n(NASDAQ:DRYS) \nI \nSeeking Alpha - Stock Market \nInsights \nI \nSeeking Alpha \nSource: rgrdlaw.com (court document) In 2012, DRYS generated \n$1.23 billion in total revenue, yet posted a  $246 million loss. In \nfact, the company has been posting losses every year for the last \nseekingalpha.com \n'Charity not the motive\" \nhttps://www.tradewindsnews.com/legal/1738610/kalani-claims-charity-not-a-motive-for-dryships-a id \nEFTA00010737\n\nKalani claims charity not a motive for DryShips \naid I  TradeWinds \nKaIani claims charity not a motive for DryShips aid Marc Bistricer-\nled investment house says it had risk and profit in mind lending \nto George Economou's struggling public company, not attempt to \nve.wv.tradewindsnews.com \nThe Toronto connection runs MUCH deeper though \nThe overlap with AQR blank check shells and Polar Asset Mgmt Toronto \nThe Toronto based Bistricer and EKONOMOU \nBistricers in New Jersey TOO! \nAND \nDAVID Bistricer happens to be a real estate developer \nhttps://www.sec.gov/cgi-bin/browse-edgar? \naction=getcompany&CIK=0001649096&owner=exclude&count=40&hidefilings=0\n1 Bistricer/Clipper \"investor\" \nToronto based C I Investments \nhttps://www.sec.gov/Archives/edgar/data/1649096/000116364819000009/0001163648-19-000009-index.htm \nCheck out this Reg D offering Bistricer/ Clipper did in Jan 2016 \nhttps://www.sec.gov/Archives/edgar/data/1649096/000161577416004014/xsIFormDX01/primary doc.xml \n$130,000 Reg D offering for this Bistricer/Clipper publicly traded \"real estate\" company was done with an \nAtlanta based firm called H&L Equities \nAtlanta is home of the obscure Trump Russia Counsel Andrew EKONOMOU \nNothing to see here. \nOf Course, then there's the Hail Mary pass Kushner threw on his Toronto based Brookfield deal for 666 5th \nAvenue \nhttps://www.thestarcom/news/world/2019/03/12/toronto-based-brookfield-faces-scrutiny-from-democrats-\nover-deal-with-kushner-company.html \nler] \nToronto-based Brookfield faces scrutiny from \nDemocrats over deal with Kushner company \nThe Star \nThe real estate giant says politics were not at all involved in its \ndecision to acquire a New York office tower from the family of \nJared Kushner, President Donald Trump's son-in-law and senior \naide. \nwww.thestarcom \nEFTA00010738\n\nwhich was brokered by Apollo/Epstein Degenerate Black/Harris/Rowan \nhttps://therealdeal.com/2018/11/15/brookfield-turns-to-apollo-for-666-fifth-financingL\n;2, \n666 Fifth I Brookfield I Apollo Global \nManagement \nPrivate equity company Apollo Global Management is funding \nBrookfield Property Partners' redevelopment of 666 Fifth Avenue \nwith a  $300 million-plus mezzanine loan, sources told The Real \nDeal ... \ntherealdeal.com \nApollo and other Kushner financing pal Blackstone just happen to be BOTH granted free reign on the US \ninsurance/annuity industry. \nCrazy shit huh? \nGreek shipping Bag man Georgios Ekonomou meets Jared Kushner \nBut it gets better still: \nStephen Feinberg: Cerberus \nhttps://www.bloomberg.com/news/articles/2018-05-11/trump-chooses-cerberus-s-feinberg-to-lead-spy-\nadvisory-panel\n;2, \nTrump Chooses Cerberus's Stephen Feinberg \nto Lead Spy Advisory Panel - Bloomberg \nPresident Donald Trump has chosen billionaire investor Stephen \nFeinberg to lead his intelligence advisory board, the White House \nsaid Friday. Trump intends to appoint Feinberg, the co-founder \nand ... \nwww.bloomberg.com \nBawag/Refco \nVirtu first bid for Knight post \"glitch\" \nand now: Money Laundering Bank HSH \nStephen Feinberg: Scum of the Earth meet Georgio EKONOMOU \nhttps://www.sec.gov/cgi-bin/browse-edgar? \naction=getcompany&CIK=0001369241&owner=exclude&count=40&hidefilings=0\nJaney, IG update my various pending TCR's and complaints \nYours VERY TRULY \nAnd INFINITELY smarter than anyone on this e mail list \nChristopher J Dilorio \nEFTA00010739\n\nWhistleblower \nFrom: Chris Dilorio \nSent: Monday, May 13, 2019 5:41 AM \nTo: \nSubject: Fw: Apollo/ Epstein/Kushner connection \nFrom: Chris Dilorio \nSent: Saturday, May 11, 2019 8:00 AM \nTo \nSubject: Fw: Apollo/ Epstein/Kushner connection \nFrom: Chris Dilorio \nSent: Monday, May 6, 2019 6:38 AM \nSubject: Fw: Apollo/ Epstein/Kushner connection \nGreetings grossly corrupt SEC et al scumbags \nAs with ALL of my allegations: beyond a shadow of a doubt, 100% accurate \nhttps://www.sec.gov/litigation/complaints/comp17673.htm \nComplaint: SEC v. \nEFTA00010740\n\nCOMPLAINT. Plaintiff United States Securities and Exchange Commission (\"Commission\") alleges as \nfollows: SUMMARY. 1. This case involves a  $15 million \"pump and dump\" scheme involving the securities \nof Environmental Solutions Worldwide, Inc. (\"Environmental\"), a public company whose common stock is \nregistered with the Commission under the Securities Exchange Act of 1934 (\"Exchange Act\"), and is ... \nwww.sec.gov \nESWW was a money laundering shell. \nThe SEC knows it. The degenerate Epstein knows it. The Degenerate Leon Black/Kushner BFF/ Milken \nproteges/Marc Rowan/Apollo knows it. \nThe DOORS knows it. \nIG, I have repeatedly offered to come to SEC DC HQ to have the brightest minds at the SEC totally humiliate me \nby refuting my allegations 1 by 1. The grossly corrupt SEC scumbags have never taken me up on my generous \noffer. For the very simple reason that ALL of my allegations are accurate and true. \nSo, I again put the offer out there: \nrefute my claims OR go to jail for the criminal obstruction ACTIVELY being facilitated by your office and the SEC. \nSo, let's give these scumbags the insurance/annuities market. \nThis will NOT end well for tens of thousands of Americans. \nWho \"green lighted\" this take over of the insurance industry by PE/Hedge funds? \nhttpsliwww.forbes.com/sites/antoinegara/2018/02/01/apollo-and-blackstone-pick-insurance-as-their-next-\nbet-to-disrupt-wall-street/#5d647dbe7689 \n;'] \nApollo And Blackstone Pick Insurance As Their \nNext Bet To Disrupt Wall Street - Forbes \nFor decades, Wall Street's gambit in insurance was to write \npolicies and use the float as a source of capital for new \ninvestments. Ifs a staple of Berkshire Hathaway and copycats like \nMarkel and ... \nwww.forbes.com \nCheers! \nChristopher Dilorio \nWhistleblower \nFrom: Chris Dilorio \nSent: Thursday, May 2, 2019 3:35 PM \nTo: \nEFTA00010741\n\nSubject: Fw: Apollo/ Epstein/Kushner \nconnection \n1G, \nThis was a blatant attempt to intimidate a whistleblower. \"HE\" (I think a male although very effeminate voice) \nwas an anonymous, coward, scumbag who threatened me. AND then called me another 11/12 times after that. \nThis is a VERY serious matter. Felony. I intend to see \"him\" prosecuted to the fullest extent of the law. Within \nweeks of filing a complaint against the SEC and you. \nI obviously have hit a nerve. \nhttps://www.nbcnews.com/politics/white-house/white-house-tells-official-who-gave-kushner-security-\nclearance-don-n997476 \nWhite House whistleblower speaks out on \nsecurity clearance controversy \nCarl Kline was supposed to appear before House committee staff \nTuesday to face questions related to his handling of White House \nsecurity clearances. \nwww.nbcnews.com \nCheers! \nChristopher Diiorio (no L's scumbag) \nFrom: Chris Dilorio \nSent: Thursday, April 25, 2019 6:27 AM \nTo: \nEFTA00010742\n\nSubject: Fw: Apollo/ Epstein/Kushner \nconnection \nESWW: A money laundering NASDAQ/OTCM shell \nMilken degenerate Leon Black/Joshua Harris: Apollo \nAND \nJeffrey Epstein \nThe SEC has known for years that Epstein is running a extortion/Ponzi/Slush Fund \nMy Claims AGAIN \nhttps://seekingalpha.com/article/3715526-environmental-solutions-worldwide-revisiting-holding-gone-dark-\ncan-sleep-better-night?mod=mw quote news \nEnvironmental Solutions Worldwide: Revisiting \nA Holding That's Gone Dark, So I Can Sleep \nBetter At Night - Environmental Solutions \nWorldwide, Inc. (OTCMKTS:ESWW) I  Seeking \nAlpha - Stock Market Insights I  Seeking Alpha \nNew CEO and recent trading activity warranted a review of a \nholding that no longer files. Based on the environment, difficult \ny/y comparisons and results from competitors, 2015 is likely a \ndown year \nseekingalpha.com \n'Not credible\"??? \nHow about the SEC's OWN words? \nhttps://www.bloomberg.com/news/articles/2018-10-0 Usec-spots-a-way-to-starve-the-most-suspicious-penny-\nstocks \nEFTA00010743\n\nSEC Spots a  Way to Starve the Most \nSuspicious Penny Stocks - Bloomberg \n\"If a company is a dark company and listed in the OTC market \nand hasn't put out financials for six months, maybe it shouldn't \nbe quoted or offered to retail investors,\" Redfearn said ... \nwww.bloomberg.com \nSee my comment letters \non this subject. \nThe SEC INTENTIONALLY puts the investing public at risk of frauds like this and thousands others like it. \nThe core biz at NITE/VIRT,CDEL etc and the reason WHY the OTCM exists: Abusive naked shorting publicly \ntraded shells to facilitate money laundering. \nShells go dark only AFTER a massive fraud has been perpetrated on the investing public: Main Street \nANOTHER \"genius\" degenerate: Apollo \nthe grossly corrupt SEC: Bought and paid for by common criminals and degenerates \nIC, I have time for that REQUIRED 3rd party cc today \nCall me \nCheers! \nChristo her Dilorio \nFrom: Chris Dilorio \nSent: Sunday, April 14, 2019 1:04 PM \nTo: \n<fl \nSubject: Fw: Apollo/ Epstein/Kushner connection \nA little Steffie Avakian//Heiss/O'Melveny/Wilmer Hale/ Apollo/Kushner Home Cooking! \nhttps://www.omm.com/professionals/howard-e-heiss/ \nEFTA00010744\n\nst \nHoward E. Heiss - O'Melveny & Myers \nHoward Heiss has an extensive litigation practice focused on \ngovernment regulatory investigations and enforcement actions, \ngrand-jury investigations, and the defense of clients in criminal \ncases, with a particular emphasis on securities matters. \nwww.omm.com \nhttps://www.sec.gov/Archives/edgar/data/1411494/000119312508077312/dsl.htm \nForm S-1- \nSEC.gov \nTable of Contents. The information in this prospectus is not complete and may be changed. The securities \nmay not be sold until the registration statement filed with the Securities and Exchange Commission is \neffective. \nwww.sec.gov \nhttps://www.wilmerhale.com/en/people/jamie-gorelick \nJamie Gorelick I \nWilmerHale \nJamie Gorelick's career has spanned the legal, policy and corporate landscapes. As one of Washington's \nbest-known litigators, Ms. Gorelick has represented corporations and individuals in a wide array of matters, \nparticularly in the regulatory and enforcement arenas, involving issues as diverse as antitrust, \nenvironmental regulation, securities enforcement, national security regulation, etc. \nwww.wilmerhale.com \nhttps://www.wilmerhale.com/en/insights/news/former-director-of-the-fbi-robert-mueller-iii-joins-wilmerhale \nFormer Director of the FBI Robert Mueller III \nJoins WilmerHale \nWilmerHale is pleased to announce that Robert S. Mueller III is \njoining the firm as a partner after serving as the sixth Director of \nthe Federal Bureau of Investigation (FBI), a position he took one \nweek prior to the September 11 attacks and held for 12 years \nunder two presidents. \nwww.wilmerhale.com \nhttps://www.sec.gov/biography/avakian-stephanie \nEFTA00010745\n\nSEC.gov I  Stephanie Avakian \nStephanie Avakian was named Co-Director of the U.S. Securities and Exchange Commission's Division of \nEnforcement in June 2017, after serving as Acting Director since December 2016. \nVAVW. \nsec goy \nSEC drops Apollo investigation after Kush Jr met with Harris at the WH \nand Apollo gives Kush's some $$$$ \nAnd, Apollo gets $60 bil+ in inflows in 2018 \nDid I miss something? \nCheers! \nYou corrupt fucking scumbags \nChristopher Dilorio \nFrom: Chris Dilorio \nSent: Saturday, April 13, 2019 11:30 AM \nTo: \nSubject: Apollo/ Epstein/Kushner connection \nFind a shell \nFind a fraud \nEnviromental Solutions Worldwide Inc \nhttps://www.sec.gov/cgi-bin/browse-edgar? \naction=getcompany&CIK=0001082278&owner=exclude&count=40&hidefilings=0\nFlorida? \nPennsylvania? \nOr \nCanada? \nEFTA00010746\n\nWelcomed on Cromwell/Wimpfheimer OTCM \nDe registered in 2015 and Frozen in time \nLiterally \nhttp://eswgroup.com/esw-group-corporate/our-board/ \nOur Board - ESW Group® \nMARK YUNG Mr Yung is Co-Founder and Managing Principal of \nOCV Management LLC (\"OCV\"), an investor, owner and operator \nof technology and life science companies based in Los Angeles. \nPreviously, Mr. Yung was a Managing Director at Orchard Capital \nCorp., a firm he joined in 2006. Through his affiliation with [...] \neswgroup.com \nDozens of filings by former Milken (ahem) right hand man Leon Black, Apollo, his family Trust, et al \nThen, \nThere's this: \nHas anyone (anyone) ever seen Pedophile Jeffrey Epstein on the other side of a trade? \nThe ONLY SEC filing of Epsteins' Financial Trust Company Inc is in \nwait for it \nLeon Black/Apollo Environmental Solutions Worldwide \nhttps://www.sec.gov/Archives/edgar/data/1082278/000090901211000390/0000909012-11-000390-index.htm \nEnter the Amicus blocking release of Epstein docs \nKrieger, Kim and Lewin \nhttps://www.kkIllp.com/ \nKrieger Kim & Lewin LLP \nWe are committed to providing the highest level of partner-driven representation in order to efficiently \nachieve client objectives. Over the last decade, we have conducted and supervised dozens of federal \ncriminal trials involving some of the highest profile and most sensitive matters prosecuted by the United \nStates Government. \nwww.kkillp.com \nFinancial fraud appears to be a specialty of this recently formed/SDNY Alum firm \nNow, \nit gets VERY interesting \nhttps://www.cnbc.com/2018/02/28/apollo-citigroup-loaned-kushner-companies-millions-new-york-times.html \nEFTA00010747\n\nTrump: Kushner's security clearance is up to \nKelly \nKushner even discussed the possibility of a White House job for \nthe founder of private equity firm Apollo, the New York Times \nreported on Tuesday. \nwww.cnbc.com \nWhere another \nMilken protege/Apollo founding partner Josh Harris was considered for a  White House job \n\"Coindences\" \nhttps://nypost.com/2018/03/02/sec-dropped-probe-month-after-firm-aided-kushner-companyj\nSEC dropped probe month after firm aided \nKushner company \nThe feds last year dropped an investigation into a financial \ncompany a month after the firm gave Jared Kushner's family real \nestate business a  $180 million loan, a new report said Friday. \nThere ... \nnypost.com \nOh, baby \n$60 billion+ inflows in 2018 for Apollo \nhttps://www.businesswire.com/news/home/20180802005343/en/Apollo-Global-Management-LLC-Reports-\nQuarter-2018 \nApollo Global Management, LLC Reports \nSecond Quarter 2018 Results I Business Wire \nNEW YORK--(BUSINESS WIRE)--Apollo Global Management, LLC \n(NYSE:APO) (together with its consolidated subsidiaries, \"Apollo\") \ntoday reported results for the second quarter ended June 30, \n2018. \nwww.businesswire.com \nMr's Krieger,Kim,Boltz et al: \nDiscovery will be a hoot! \nEFTA00010748\n\nFucking A \nI  am \ngood \nCheers! \nChristopher Dilorio \nEFTA00010749",
    "pageCount": 26,
    "dataset": "Dataset 8"
  },
  "entities": {
    "people": [
      {
        "name": "Jeffrey Epstein",
        "role": "extracted",
        "context": "19/07/10/business/jeffrey-epstein-net-worth.html \nJeffrey Epstein's 'Infinite Means' May Be a Mirage \nMr. Epstein,"
      },
      {
        "name": "Donald Trump",
        "role": "extracted",
        "context": "-fundraiser-at-\nnursing-home-magnates-house.html \nDonald Trump coming to Cleveland Friday for \nfundraiser at nur"
      },
      {
        "name": "Epstein",
        "role": "extracted",
        "context": "inite Means' May Be a Mirage \nMr. Epstein, facing sex-trafficking c"
      },
      {
        "name": "Gorelick",
        "role": "extracted",
        "context": "ton's \nbest-known litigators, Ms. Gorelick has represented corporati"
      },
      {
        "name": "Yung",
        "role": "extracted",
        "context": "in Los Angeles. \nPreviously, Mr. Yung was a Managing Director a"
      },
      {
        "name": "Chris \nDilorio",
        "role": "extracted",
        "context": "From: Chris \nDilorio \nTo: \nSubject: Fw: Apollo/ Ep"
      },
      {
        "name": "Legal Information",
        "role": "extracted",
        "context": "U.S. \nCode I US Law \nI \n0 \n/ Legal Information \nInstitute \nto obtain, by mea"
      },
      {
        "name": "Chad \nReadier",
        "role": "extracted",
        "context": "https://en.wikipedia.org/wiki/Chad \nReadier \nChad Readler - Wikipedia \nAu"
      },
      {
        "name": "Chad Readler",
        "role": "extracted",
        "context": "pedia.org/wiki/Chad \nReadier \nChad Readler - Wikipedia \nAugust 23, 1972"
      },
      {
        "name": "Wikipedia \nAugust",
        "role": "extracted",
        "context": "Chad \nReadier \nChad Readler - Wikipedia \nAugust 23, 1972 (age 46) Pontiac, Mi"
      },
      {
        "name": "Chad Andrew",
        "role": "extracted",
        "context": "versity of Michigan (BA, JD): Chad Andrew Readler (born \nAugust 23, 197"
      },
      {
        "name": "Circuit Judge",
        "role": "extracted",
        "context": "23, 1972) is a United States Circuit Judge of the United \nStates Court o"
      },
      {
        "name": "United \nStates",
        "role": "extracted",
        "context": "d States Circuit Judge of the United \nStates Court of Appeals for the Sixt"
      },
      {
        "name": "Sixth Circuit",
        "role": "extracted",
        "context": "ates Court of Appeals for the Sixth Circuit and former Principal \nDeputy"
      },
      {
        "name": "Principal \nDeputy",
        "role": "extracted",
        "context": "the Sixth Circuit and former Principal \nDeputy and former Acting Assistant A"
      },
      {
        "name": "Acting Assistant",
        "role": "extracted",
        "context": "Principal \nDeputy and former Acting Assistant Attorney General for the \nen."
      },
      {
        "name": "Attorney General",
        "role": "extracted",
        "context": "y and former Acting Assistant Attorney General for the \nen.wikipedia.org \nTh"
      },
      {
        "name": "White House",
        "role": "extracted",
        "context": "minality associated with this White House is off the charts. \nCalk: Lor"
      },
      {
        "name": "Lorber \nLorber",
        "role": "extracted",
        "context": "use is off the charts. \nCalk: Lorber \nLorber/Elliman/lcahn: Frost/Honig/St"
      },
      {
        "name": "Alpha Capital",
        "role": "extracted",
        "context": "hn: Frost/Honig/Stetson \nAND \nAlpha Capital: Martin Schlaff: MY CLAIMS \nL"
      },
      {
        "name": "Martin Schlaff",
        "role": "extracted",
        "context": "/Stetson \nAND \nAlpha Capital: Martin Schlaff: MY CLAIMS \nLadenburg/Gruntal"
      },
      {
        "name": "Bawag \nAlso",
        "role": "extracted",
        "context": "IMS \nLadenburg/Gruntal: Refco/Bawag \nAlso Schlaff AND: Englander/Nordli"
      },
      {
        "name": "Scan Graphics",
        "role": "extracted",
        "context": "litate $$ laundering: Sedona/ Scan Graphics \nMy claims: NITE/VIRT: Refco"
      },
      {
        "name": "Schwarzman \nEpstein",
        "role": "extracted",
        "context": "ere glitchy glitchy \nEpstein: Schwarzman \nEpstein: Black \nBlack/Schwarzman: Kus"
      },
      {
        "name": "Black \nBlack",
        "role": "extracted",
        "context": "Epstein: Schwarzman \nEpstein: Black \nBlack/Schwarzman: Kushner (my BX SE"
      },
      {
        "name": "Sull Crom",
        "role": "extracted",
        "context": "EC NITE/VIRT obstruction: Jay/Sull Crom/Fishman \n1MDB: PHUN/Nordlicht"
      },
      {
        "name": "Bistricers \nFeinberg",
        "role": "extracted",
        "context": "shippers \nEconomou/EKONOMOU \nBistricers \nFeinberg: Danaos \nTrump attorney: EKON"
      },
      {
        "name": "Danaos \nTrump",
        "role": "extracted",
        "context": "ONOMOU \nBistricers \nFeinberg: Danaos \nTrump attorney: EKONOMOU \nBarr 1MDB"
      },
      {
        "name": "Chris Dilorio",
        "role": "extracted",
        "context": "Iololol \nEFTA00010725\n\nFrom: Chris Dilorio \nSent: Saturday, July 13, 201"
      },
      {
        "name": "Trump Ohio",
        "role": "extracted",
        "context": "Kushner connection \nMore.... \nTrump Ohio fundraiser \nBrian Colleran \nh"
      },
      {
        "name": "Brian Colleran",
        "role": "extracted",
        "context": "e.... \nTrump Ohio fundraiser \nBrian Colleran \nhttps://www.cleveland.com/po"
      },
      {
        "name": "Cleveland Friday",
        "role": "extracted",
        "context": ".html \nDonald Trump coming to Cleveland Friday for \nfundraiser at nursing ho"
      },
      {
        "name": "Republican President",
        "role": "extracted",
        "context": "eland.com \nCLEVELAND, Ohio —  Republican President Donald Trump is \nvisiting Cle"
      },
      {
        "name": "Three Companies",
        "role": "extracted",
        "context": "t-\nallegations \nEFTA00010726\n\nThree Companies and Their Executives Pay $19."
      },
      {
        "name": "Their Executives",
        "role": "extracted",
        "context": "00010726\n\nThree Companies and Their Executives Pay $19.5 \nMillion to Resolve"
      },
      {
        "name": "Resolve False",
        "role": "extracted",
        "context": "cutives Pay $19.5 \nMillion to Resolve False Claims Act Allegations \nPerta"
      },
      {
        "name": "Claims Act",
        "role": "extracted",
        "context": "9.5 \nMillion to Resolve False Claims Act Allegations \nPertaining to Re"
      },
      {
        "name": "Allegations \nPertaining",
        "role": "extracted",
        "context": "n to Resolve False Claims Act Allegations \nPertaining to Rehabilitation Therapy and"
      },
      {
        "name": "Rehabilitation Therapy",
        "role": "extracted",
        "context": "ct Allegations \nPertaining to Rehabilitation Therapy and Hospice \nServices I OPA I"
      },
      {
        "name": "Hospice \nServices",
        "role": "extracted",
        "context": "to Rehabilitation Therapy and Hospice \nServices I OPA I Department of Justice"
      },
      {
        "name": "Justice \nOhio",
        "role": "extracted",
        "context": "ervices I OPA I Department of Justice \nOhio based Foundations Health Solu"
      },
      {
        "name": "Foundations Health",
        "role": "extracted",
        "context": "rtment of Justice \nOhio based Foundations Health Solutions Inc. (FHS), Olympia"
      },
      {
        "name": "Solutions Inc",
        "role": "extracted",
        "context": "Ohio based Foundations Health Solutions Inc. (FHS), Olympia Therapy Inc."
      },
      {
        "name": "Olympia Therapy",
        "role": "extracted",
        "context": "Health Solutions Inc. (FHS), Olympia Therapy Inc. \n(Olympia), and India Ho"
      },
      {
        "name": "India Hospice",
        "role": "extracted",
        "context": "Therapy Inc. \n(Olympia), and India Hospice Care Inc. (Tridia), and their"
      },
      {
        "name": "Care Inc",
        "role": "extracted",
        "context": "(Olympia), and India Hospice Care Inc. (Tridia), and their executiv"
      },
      {
        "name": "Brian \nColleran",
        "role": "extracted",
        "context": "ridia), and their executives, Brian \nColleran (Colleran) and Daniel Parker"
      },
      {
        "name": "Daniel Parker",
        "role": "extracted",
        "context": "rian \nColleran (Colleran) and Daniel Parker (Parker), have agreed to pay"
      },
      {
        "name": "Another Honig",
        "role": "extracted",
        "context": "and hospice \nwwwjustice.gov \nAnother Honig $$$ laundering shell \nInterge"
      },
      {
        "name": "Intergetics \nMillenium",
        "role": "extracted",
        "context": "r Honig $$$ laundering shell \nIntergetics \nMillenium \nNMC \nRegent \ntake your pick"
      },
      {
        "name": "Christopher Dilorio",
        "role": "extracted",
        "context": "08-023159-index.htm \nCheers! \nChristopher Dilorio \nand \nFrom: Chris Dilorio \nSe"
      },
      {
        "name": "Mr Berman",
        "role": "extracted",
        "context": "/ Epstein/Kushner connection \nMr Berman, \nThanks for the shout out, b"
      },
      {
        "name": "Infinite Means",
        "role": "extracted",
        "context": "orth.html \nJeffrey Epstein's 'Infinite Means' May Be a Mirage \nMr. Epstein"
      },
      {
        "name": "May Be",
        "role": "extracted",
        "context": "ey Epstein's 'Infinite Means' May Be a Mirage \nMr. Epstein, facing"
      },
      {
        "name": "Mirage \nMr",
        "role": "extracted",
        "context": "n's 'Infinite Means' May Be a Mirage \nMr. Epstein, facing sex-traffick"
      },
      {
        "name": "Greetings Grossly",
        "role": "extracted",
        "context": "/ Epstein/Kushner connection \nGreetings Grossly corrupt SEC scumbags et al \nI"
      },
      {
        "name": "Berger Montague",
        "role": "extracted",
        "context": "13 TCR filed with prestigious Berger Montague \nEFTA00010728\n\nMore AML flags"
      },
      {
        "name": "Alpha Cap",
        "role": "extracted",
        "context": "gain. \nMartin Schlaff/Balmore/Alpha Cap \nhttps://www.haaretz.com/isra"
      },
      {
        "name": "Bag Man",
        "role": "extracted",
        "context": "t-\n1.5457018 \nMartin Schlaff: Bag Man \nBut it gets MUCH better \nGra"
      },
      {
        "name": "Filing Documents",
        "role": "extracted",
        "context": "-16-427770-i ndex. htm \nEDGAR Filing Documents for 0001193125-16-427770 \nGra"
      },
      {
        "name": "Tech Global",
        "role": "extracted",
        "context": "for 0001193125-16-427770 \nGrafTech Global Enterprises Inc. (Filer) CIK:"
      },
      {
        "name": "Enterprises Inc",
        "role": "extracted",
        "context": "25-16-427770 \nGrafTech Global Enterprises Inc. (Filer) CIK: 0000940404 (see"
      },
      {
        "name": "Fiscal Year",
        "role": "extracted",
        "context": "5602 I State \nof Incorp.:DE I Fiscal Year End: 1231 Type: 15-15D I Act"
      },
      {
        "name": "Wall Street",
        "role": "extracted",
        "context": "Milikowsky \nwww.haaretz.com \nWall Street / CNBC Wiz Karen Finerman \n\"S"
      },
      {
        "name": "Wiz Karen",
        "role": "extracted",
        "context": "aretz.com \nWall Street / CNBC Wiz Karen Finerman \n\"Save Graft etc\" \nh"
      },
      {
        "name": "Save Graft",
        "role": "extracted",
        "context": "t / CNBC Wiz Karen Finerman \n\"Save Graft etc\" \nhttps://www.sec.gov/Arc"
      },
      {
        "name": "Save Graf",
        "role": "extracted",
        "context": "NEW YORK, January 23, 2015 -  Save GrafTech, an investor group led by"
      },
      {
        "name": "Nathan Milikowsky",
        "role": "extracted",
        "context": "ech, an investor group led by Nathan Milikowsky, a holder of \nover 15 million"
      },
      {
        "name": "Tech International",
        "role": "extracted",
        "context": "%, of the common stock of GrafTech International Ltd. (NYSE: GTI), today \nsent"
      },
      {
        "name": "Tech Board",
        "role": "extracted",
        "context": "day \nsent a letter to the GrafTech Board of Directors disclosing that"
      },
      {
        "name": "Securities Act",
        "role": "extracted",
        "context": "ce with Rule 457(c) under the Securities Act of 1933, as amended, based up"
      },
      {
        "name": "Rare \nEarth",
        "role": "extracted",
        "context": "Aluminum, Copper, \nStainless, Rare \nEarth, Metal Prices, Forecasting I"
      },
      {
        "name": "Metal Prices",
        "role": "extracted",
        "context": "per, \nStainless, Rare \nEarth, Metal Prices, Forecasting I MetalMiner \nNe"
      },
      {
        "name": "Miner \nNeedle",
        "role": "extracted",
        "context": "al Prices, Forecasting I MetalMiner \nNeedle coke, a crude oil derivative,"
      },
      {
        "name": "Main Street",
        "role": "extracted",
        "context": "ossly corrupt SEC \"protecting Main Street as usual\" \nFraud certainly no"
      },
      {
        "name": "Mr Teotia",
        "role": "extracted",
        "context": "nly not limited to the \nOTCM \nMr Teotia, \ncongrats on taking Wes Bric"
      },
      {
        "name": "Wes Bricker",
        "role": "extracted",
        "context": "r Teotia, \ncongrats on taking Wes Bricker's job \nno doubt you're workin"
      },
      {
        "name": "Mr Transparency",
        "role": "extracted",
        "context": "financials not \"published\" by Mr Transparency Dougie \nCifu. \nWhere would a"
      },
      {
        "name": "Dougie \nCifu",
        "role": "extracted",
        "context": "published\" by Mr Transparency Dougie \nCifu. \nWhere would a $4 billion+ w"
      },
      {
        "name": "Ditorio \nFrom",
        "role": "extracted",
        "context": "acy.... \nCheers! \nChristo her Ditorio \nFrom: Chris Dilorio < \nSent: Wedne"
      },
      {
        "name": "Ms Strauss",
        "role": "extracted",
        "context": "er connection \nGetting warmer Ms Strauss \nhttgs://www.justice.gov/usao"
      },
      {
        "name": "Calk Charged",
        "role": "extracted",
        "context": "stration \nBank CEO Stephen M. Calk Charged With Corruptly \nSoliciting A"
      },
      {
        "name": "With Corruptly",
        "role": "extracted",
        "context": "k CEO Stephen M. Calk Charged With Corruptly \nSoliciting A Presidential Ad"
      },
      {
        "name": "Presidential Administration",
        "role": "extracted",
        "context": "With Corruptly \nSoliciting A Presidential Administration Position In \nExchange For App"
      },
      {
        "name": "Position In",
        "role": "extracted",
        "context": "A Presidential Administration Position In \nExchange For Approving $16 M"
      },
      {
        "name": "Exchange For",
        "role": "extracted",
        "context": "l Administration Position In \nExchange For Approving $16 Million In Loan"
      },
      {
        "name": "Million In",
        "role": "extracted",
        "context": "n \nExchange For Approving $16 Million In Loans I USAO-\nSDNY I Departme"
      },
      {
        "name": "Justice \nAudrey",
        "role": "extracted",
        "context": "I USAO-\nSDNY I Department of Justice \nAudrey Strauss, the Attorney for the"
      },
      {
        "name": "Acting Under",
        "role": "extracted",
        "context": "torney for the United States, Acting Under Authority \nConferred by 28 U."
      },
      {
        "name": "Authority \nConferred",
        "role": "extracted",
        "context": "e United States, Acting Under Authority \nConferred by 28 U.S.C. §  515, William"
      },
      {
        "name": "Sweeney Jr",
        "role": "extracted",
        "context": "28 U.S.C. §  515, William F.  Sweeney Jr, the Assistant Director-in-\nE"
      },
      {
        "name": "Assistant Director",
        "role": "extracted",
        "context": ", William F.  Sweeney Jr, the Assistant Director-in-\nEFTA00010731\n\nCharge of t"
      },
      {
        "name": "Field Office",
        "role": "extracted",
        "context": "10731\n\nCharge of the New York Field Office of the Federal Bureau of Inve"
      },
      {
        "name": "Federal Bureau",
        "role": "extracted",
        "context": "New York Field Office of the Federal Bureau of Investigation \n(\"FBI\"), an"
      },
      {
        "name": "Patricia Tarasca",
        "role": "extracted",
        "context": "f Investigation \n(\"FBI\"), and Patricia Tarasca, the Special Agent-in-Charge"
      },
      {
        "name": "Special Agent",
        "role": "extracted",
        "context": "\"), and Patricia Tarasca, the Special Agent-in-Charge of the New York \nww"
      },
      {
        "name": "Trump \nLorber",
        "role": "extracted",
        "context": "the end \nCalk/Lorber/Elliman: Trump \nLorber: New Valley Corp \nhttps://www"
      },
      {
        "name": "New Valley",
        "role": "extracted",
        "context": "orber/Elliman: Trump \nLorber: New Valley Corp \nhttps://www.sec.gov/Arc"
      },
      {
        "name": "Apollo Moscow",
        "role": "extracted",
        "context": "014405003084/g93826e10vk.htm \nApollo Moscow/Kremlin development \nAND \nLad"
      },
      {
        "name": "Ladenburg Thalman",
        "role": "extracted",
        "context": "cow/Kremlin development \nAND \nLadenburg Thalman \nI asked in previous correspo"
      }
    ],
    "locations": [
      {
        "name": "Miami",
        "type": "location"
      },
      {
        "name": "Janey, IG",
        "type": "city"
      }
    ],
    "dates": [
      {
        "date": "2018-05-11",
        "event": "2018-05-11"
      },
      {
        "date": "1972-08-23",
        "event": "August 23, 1972"
      },
      {
        "date": "2019-07-13",
        "event": "July 13, 2019"
      },
      {
        "date": "2019-07-11",
        "event": "July 11, 2019"
      },
      {
        "date": "2019-07-08",
        "event": "July 8, 2019"
      },
      {
        "date": "2015-01-23",
        "event": "January 23, 2015"
      },
      {
        "date": "2019-06-26",
        "event": "June 26, 2019"
      },
      {
        "date": "2019-06-25",
        "event": "June 25, 2019"
      },
      {
        "date": "2019-05-24",
        "event": "May 24, 2019"
      },
      {
        "date": "2019-05-23",
        "event": "May 23, 2019"
      },
      {
        "date": "2019-05-19",
        "event": "May 19, 2019"
      },
      {
        "date": "2019-05-17",
        "event": "May 17, 2019"
      },
      {
        "date": "2019-05-15",
        "event": "May 15, 2019"
      },
      {
        "date": "2019-05-13",
        "event": "May 13, 2019"
      },
      {
        "date": "2019-05-11",
        "event": "May 11, 2019"
      },
      {
        "date": "2019-05-06",
        "event": "May 6, 2019"
      },
      {
        "date": "2019-05-02",
        "event": "May 2, 2019"
      },
      {
        "date": "2019-04-25",
        "event": "April 25, 2019"
      },
      {
        "date": "2019-04-14",
        "event": "April 14, 2019"
      },
      {
        "date": "2019-04-13",
        "event": "April 13, 2019"
      },
      {
        "date": "2018-06-30",
        "event": "June 30, \n2018"
      }
    ],
    "flights": [],
    "phone_numbers": [
      "0000072170",
      "0001144204",
      "0001193125",
      "0000940404",
      "1536608366",
      "0000922423",
      "0001003740",
      "0001649096",
      "0001163648",
      "0001369241",
      "0001082278",
      "0000909012"
    ],
    "organizations": []
  },
  "processedAt": "2025-12-23T12:25:42.483Z"
}