{
  "document": {
    "id": "efta00014685",
    "filename": "EFTA00014685.pdf",
    "path": "C:\\Users\\user\\CascadeProjects\\epsteinexposed\\apps\\web\\DataSet 8\\VOL00008\\IMAGES\\0002\\EFTA00014685.pdf",
    "text": "\n\n09 \nJPMorgan Chase Bank \n2002 \nNew York. NY 10154-1002 \nAccount Number \n• \nJEFFREY EPSTEIN \nJPMorgan Private Bank \nConfidential Page 1 of 9 \nAsset Account \nPortfolio \nSeptember I - September \n30, 2002 \nTable of Contents \nPage \nPortfolio Summary \n2 \nCash and \nShort Term \n3 \nTrade Activity 5 \nAccount Transactions 6 \nAccount Officers \nService Specialist \nRILEYIHORNBECKER \n000000 0000 00 0000000000000020 COX00 \nJEFFREY E EPSTEIN \nC/O FINANCIAL TRUST COMPANY \nATTN JEANNE BRENNAN \nST \nTHOMAS VI 00802 \nGOVERNMENT \nEXHIBIT \n504 \n52 20 Cr. 330 (MN) \nConfidential Treatment Requested by JPMorgan \nChase \nJPM-SDNY-00005505 \nEFTA00014685\n\n09 \nJPMorgan Chase Bank \n2002 New York, NY 10154-1002 \nAccount Number.\nJEFFREY EPSTEIN \nPortfolio Summary \nExcept kr the Depcwt Acta\"! (e ~ir) end the osen sn pro Aue( notam( \n(Mon \nn maure° dapOUIS wrtn.IPMCI) nr» of Me \"...nemme rekna/ tn (hm stammen: \nof yre Aser notam( 'menene ~ml fonds ro FOPC munn% of benk depcorts \nObkg•bovg of Of gvaiar4000 by JANCO of (my o( on bank av trwer offhtwes ((mins \nOVIgnuu9e md.:0W) \nSven \nSOCurgain and otnrommtments ro sotra k, \"remmen; \nna&ameiude)9 \nPass«. \nbas c( inong~ ~Nag ~nagd Soo 'Importen( \ninformation obo& gauv JPMSP EkoMene Aceount cg the end ot the Aszet Accourd \n~ho \nAsset Account Portfolio \nSeptember 01, 2002 • September 30, 2002 \nfl\nJPMorgan Private Bank \nPage 2 of 9 \nOverview \nCash & \nShort Term \nrenke( Vera 1.1S0 \n54030 \n6,838,687.24 \nlirker Valpe US() \nAur3f \n14,816,643.79 \nTotal 6,838,687.24 14,816,643.79 \nAccrued Income 11,992 75 22,043 45 \nTotal Portfolio Value 6,850,679.99 14,838,687.24 \nTex \nCOM USO \n6,838,687.24 \n6,838,687.24 \nEnlmetee \nAnnua( \nincom• (,30 \n109,416.12 \n109,416.12 \nAsset Allocation \n100% Cash and Short Term \nIncome Summary \nThls Perler USD Vw to Dele USD` \nTaxable Interest 949.99 949.99 \nU.S. Tax Exempt Dividends 21,093.46 \n21,475.74 \nTotal 22,043.45 \n22,425.73 \nContidential Treatment Requested by JPMorgan JPM-SDNY-00005506 \nChase \nEFTA00014686\n\n09 \n2002 \nAccount Number.\nJEFFREY EPSTEIN September 01, 2002 - September 30, 2002 \nJPMorgan Chase Bank \nNew York, NY 10154-1002 \nJPMorgan Private Bank \nAsset Account Portfolio Page 3 of 9 \nCash and \nShort Term \nSummary by Maturity \nCurrent Starner Value Estimated Annual Income \nUSO \nUSO \nCash 957.08 \n12.44 \nLess Than 3 Months 6,837,730.16 109,403.68 \nTotal 6,838,687.24 \n109,416.12 \nCurrent yield is displayed for instruments with no maturity and YTM on market is displayed for instruments that mature. \nCash and Short Term by Type \nOescription \nCusipSeanatoody's Rating dummy Quantify \nWarded( \nnid \nOriginal \nMarker \nPrice \nTax Cost \nnd \nOriginal \nCUMIN \nMarker Wks USD \nEstimated \nUnrearae4 \nAnnual \nON/14.055 USO Income USD \nCurrent \nYMIM \nVIM % ACCILIOCI MIMS( USO \nCash \nJP MORGAN TAX FREE MONEY MARKET USD 957.08 1.00 1.00 957.08 957.08 12.44 1.30 \nPREMIER CLASS SWEEP FUND (92) 0.83 \n(SWEEP DEADLINE IS 11:30 AM EST) \n7-Day Annualized Yield: 1.27% \nShort Term by Maturity \nJ P MORGAN TAX FREE MONEY MARKET \nUSD 6,837,730.16 1.00 \n1.00 6,837,730.16 \n6,837,730.16 109,403.68 1.60 \nFUND \nINSTITUTIONAL SHARE CLASS 11,991.92 \n(FUND 840) \n7-Da Annualized Yield: \n1.52% \nConfidential Treatment Requested by JPMorgan JPM-SDNY-00005507 \nChase \nEFTA00014687\n\n09 \nAccount Number \nJEFFREY EPSTEIN September 01, 2002 - September 30, 2002 \nJPMorgan \nChase Bank \n2002 \nNew \nYork, \nNY 10154-1002 \n°JPMorgan Private Bank \nAsset Account Portfolio Page 4 of 9 \nCash and Short Term by Type continued \nDesorption \nCusipS&P Moody's Rating \nUnir Cost Tax Coat Covent \nEstimated Current \nStstso' \nMania \nAtiped  \nMargot \nValue USO Unrealized \nAnnual Weld' \nCurrency Ouantiry Original Price Original Accrued Interest USO Galatoss USO Income \nUSO WM \nTotal Cash and Short Term \nimportant Information ~U. Pricing and Valuations \nRipen \nsome or went \nare \ngraded by prang Serr, Ce3 a OW« \nSWOP, \nrh \ne deem meet% we not gueranteed b ~Pea aas terazahle valuer \n6,838,687.24 6,838,687.24 0.00 109,416.12 1.60 \n11,992.75 \nConfidential Treatment Requested by JPMorgan JPM-SDNY-00005508 \nChase \nEFTA00014688\n\n09 \nJPMorgan Chase Bank \n2002 New York, NY 10154-1002 \nAccount Number.\nJEFFREY EPSTEIN \nTrade Activity \nAsset Account Portfolio \nSeptember 01, 2002 - September 30, 2002 \nJPMorgan Private Bank \nPage 5 of 9 \nRealized Gain/Loss Summary \nShort Term Gain/Loss \nLong Term Gain/Loss \nNote: S incicates Short Term Realized Gain/Loss \nL indicates Long Term Realized Gain/Loss \nCapital gains and losses on sales with missing or incomplete tax cost are identified with WA. \nAmount USD \n0.00 \n0.00 \nTrade Activity by Type \nTrade Semement \nCare Clare Type \nOeungifIon \nCurrency Quantify P/1OVUM \nName CostoProcels \nRealized \nTax \nCOW Gainless 050 \nSettled \nAug 30 Sep 3 Purchase J P MORGAN TAX FREE MONEY MARKET \nUSD 21,086 37 1.00 \n- 21,086.37 \nFUND INSTITUTIONAL SHARE CLASS \n(FUND 84O) \nSep 10 Sep 10 Sale J P MORGAN TAX FREE MONEY MARKET USD - 2,000,000 1.00 2,000,000.00 - 2,000,000.00 \nFUND \nINSTITUTIONAL SHARE CLASS \n(FUND 840) \nSep 16 Sep 16 Sale J P MORGAN TAX FREE MONEY MARKET USD - 1,000,000 1.00 1,000,000.00 - 1,000,000.00 \nFUND INSTITUTIONAL SHARE CLASS \n(FUND 840) \nSep 18 Sep 18 Sale \nJ P MORGAN TAX FREE MONEY MARKET \nUSD - 5,000,000 1.00 5,000,000.00 - 5,000,000.00 \nFUND INSTITUTIONAL SHARE CLASS \n(FUND 840) \nConfidential Treatment Requested by JPMorgan JPM-SDNY-00005509 \nChase \nEFTA00014689\n\n09 \n2002 \nAccount Number.\nJEFFREY EPSTEIN September 01, 2002 - September 30, 2002 \nJPMorgan Chase Bank \nNew York. NY 10154-1002 \nJPMorgan Private Bank \nAsset Account Portfolio Page Got 9 \nAccount Transactions \nCash Activity Summary \nAmount1MS \nPenod USD \nAmount \nYear \nto Date USD' \nBeginning Balance \nCredits \n.00 \nDividends 21,093 46 21.475 74 \nTaxable Interest 949.99 949.99 \nSweep Account Sales 48,998.65 \nSales, Maturities, Redemptions 8,000,000.00 18,000,000.00 \nMiscellaneous Receipts 24,767,645.14 \nDebits \nSweep Account Purchases - 957.08 \n- \n1,339.36 \nPurchases of Securities - 21,086.37 - 24,837,730.16 \nMiscellaneous Disbursements - 8,000,000.00 - 18,000,000.00 \nEnding Balance .00 \n*Year to date information is calculated on a calendar year basis. \nActivity by Date \nSettlement \nare Type Quantity Descnplton Amount USD \nSep 3 Dividend \nSep 3 Interest \nJP MORGAN TAX FREE MONEY MARKET \nPREMIER \nCLASS SWEEP FUND (92) \n(SWEEP DEADLINE IS 11:30 AM EST) \nINTEREST FOR AUG. @ 1.4% ON NET \nAVERAGE COLLECTED BALANCE \n$798,956.29 \nAS OF 09/01/02 \n7.09 \n949.99 \nConfidential Treatment Requested by JPMorgan JPM-SDNY-00005510 \nChase \nEFTA00014690\n\n09 \nAccount Number.\nJEFFREY EPSTEIN September 01, 2002 • September 30, 2002 \nJP111organ Chum: Bank \n2002 New York, NY 10154-1002 \nq1PMorgan Private Bank \nAsset Account Portfolio Page 7 of 9 \nActivity by Date \nSealentenz \nOne \nTYPe \ncontinued \nGummy DeSCOMM \nAmount \nVW \nSep 3 \nSep 3 \nDividend \nPurchase 21,086.37 \nJ P MORGAN TAX FREE MONEY MARKET \nFUND INSTITUTIONAL SHARE CLASS \n(FUND 840) \nJ P MORGAN TAX FREE MONEY MARKET \nFUND INSTITUTIONAL SHARE CLASS \n(FUND 840) \nINCOME DIVIDEND \nREINVESTED a $1.00 \nJ.P.MORGAN SECURITIES INC AS AGENT \nTRADE \nDATE 08/30/02 \n21,086 \n37 \n- 21,086.37 \nSep 3 Purchase 957.08 JP \nMORGAN TAX FREE MONEY MARKET \n- 957.08 \nPREMIER CLASS SWEEP FUND (92) \n(SWEEP DEADLINE IS 11:30 AM EST) \nSep 10 Sale - 2,000,000 J P MORGAN TAX \nFREE MONEY MARKET \n2,000,000 00 \nFUND INSTITUTIONAL SHARE CLASS \n(FUND 840) \nJ.P.MORGAN SECURITIES INC AS AGENT \na 1.00 \nTRADE DATE 09/10/02 \nSep 10 Misc. Disbursement \nTRANSFERRED BY WIRE \nTO - 2,000,000.00 \nPALM BEACH NATL BK 8 TR CO \nFAO JEFFREY EPSTEIN \nLETTER FROM CLIENT \nSep 16 Sale - 1,000,000 J P MORGAN TAX FREE MONEY MARKET \n1,000,000 00 \nFUND INSTITUTIONAL SHARE CLASS \n(FUND 840) \nJ.P.MORGAN SECURITIES INC AS AGENT \na 1.00 \nTRADE DATE 09/16/02 \nConfidential Treatment Requested by JPMorgan JPM-SDNY-00005511 \nChase \nEFTA00014691\n\n09 \nAccount Number.\nJEFFREY EPSTEIN September 01, 2002 • September 30, 2002 \nJPMorgan Chas: Bank \n2002 New York, NY 10154-1002 \nq1PMorgan Private Bank \nAsset Account Portfolio Page Sof 9 \nActivity by Date \nSealenteen \nOne type \ncontinued \nGummy Descraalon Amounr USD \nSep 16 Misc. \nDisbursement TRANSFERRED BY \nWIRE TO - 1,000,000 00 \nPALM \nBEACH NATI BK 8 TR CO \nFAO \nJEFFREY EPSTEIN \nLETTER FROM CLIENT \nSep 18 Sale - 5,000,000 J P MORGAN TAX FREE MONEY MARKET 5,000,000 00 \nFUND INSTITUTIONAL SHARE CLASS \n(FUND 840) \nJ.P.MORGAN SECURITIES INC AS AGENT \nSep 18 Misc. Disbursement \na 1.00 \nTRADE \nDATE 09/18/02 \nTRANSFERRED BY \nWIRE TO \nPALM BEACH NATL BK 8 TR CO \nFAO GHISLAINE MAXWELL \nLETTER \nFROM CLIENT \n- 5,000,000.00 \nConfidential Treatment Requested by JPMorgan JPM-SDNY-00005512 \nChase \nEFTA00014692\n\n09 \n1001\nAccount Number \nJEFFREY EPSTEIN September 01, 2002 - September 30. 2002 \nJPMorgan \nChase Bank \nNen \nYork, \nNY 10154-1002 \nJPNlorgan Private Bank \nAsset Account Portfolio \nPact: C.) \nof C: \nIn \nCase of Erma or Questions About \nYour \nSabena Transfers. \nContact bow Mogan Teem at abed me wwwpwooe runvuus on the front \ndine \nstatement°, nice us at 500 Stanton ChnstanoRoad. LOPS, Nowak CIE 10713-2107 as \nnoon \nas mica. el you (AM woe staternont is wrong a I  sou need Mae \nanforeretronatnot • WSW \non \nme statement We must nee,  \nmom \nyou no IOW than CO days, atter ee sent you Me FIRSTstelement on which the arrow  pastern appeared (  )  Ton us \n>0W\n mono an account nuntor (2)DesaneSe Mate \nto \nMinster you are WWIa about and expawas Mat as \nyou can shy you oetevert is \nin \nincur why >Ou need more +Mammon (3) \nfed \nus the dose...moat of Pro SuSpaCled too. If you contact us orgy yaw must send us yap conplant a Question ,n wnnno sal 10 business days in ado* to presseywyout runts We WAY \nolveStyaleyOur COMplatn: and va Correct \nany \nera iyorpoy It we take erria \nthan \n10 ousmway days ro do this (20days Ice purameausno yow timecard ce anternanonoltrensacbons) we val cad, t woe asount fa me \namount \nyX, Hulk U \nn \nand \nSO the( yew Mr Mae \nthe use or frOney dam; He an* 4 fain us \nto \nCOmpanteOunn.estgaton \nM as a area or questions about your statement, including yew tine of credit. \nif you thmic that jots statement a incarect a (you need mete ficrmabon about a bansecton on put Maternent including a kr& of cred.f tense:Um you must ado bus on a secaate sheet describing the face and sans:etc JPMorgan \nAlva. Bank 500 Stanton CITASNMa Road. l/OPS3 \nNowak \nOE 107134107. We must his ban pal no ate than 60 days Me' me Matron. on whch 070 era or peobtam appeared is sad You can contact sour dantsewn. somata! but \nsloop so nes not enamor your ryas \nIn your Man plowse pond* the kituang ofeemiston (Shea name and account number \n(2) \nOws donor amount of the sospocled ever and (3)• dowager, of the arse end expeinatcrt ✓you con why you bedew then is an ono. If you need \nmore infarreebon you must Marto the Own you we unsure about \nThe allergen Funds or rho -Morgan InatIrtational Funds or The American Century Fends \nJP Morgan Funds Disbnufas Ire o the distributer \nof \nthe J P Morgan Fords end AmericanCentury Investment Seams Inc is the Waimea sifts Amman Century Funds \"Meagan Investment Manaderrent Mc and Arnencon Century Investment Alanagarrant save as \n.nvestment Mons to Mee respective Itna rennia3 Snores of the funds be net WM deposes end we not ameenfeedDy any bank government entity. a Me FOIC. Ram and shwepnas \nwit \nNCNB* end redact:4)am nave may be more alms than airs,  ast WM@ the \nmeneymelkel fun& se\nek \nto mantel,' a slable net easel yoked $IMI per Share. then le nO SMUlancetnet they \nwit \ncontinueto do so. Theostinted annual mammal dreidendyieW figums \nfor \nnaval funds apemen/ the funds' most 'scent income &Wend demote& \nIf you have Owen one of tie \nsweep mutual \nfunds you aye nobled Mal \nportion in \nme \nAna Money \nMake Sweep \nFund \nntordoord \nhoOmos its \nthe \"'Wildman \nPOMO Wet \"VW \nFund. \nP 7M 0 M \nMe\n Fedora,\n they \nMMAM \nSheep \nFund \nrepresent holdings h the JPOkroan Fedeal Money Market Food and porton, vo the nix Exalt( Money Make( Sweep Fund represent holdags in the JPIAcegon Tax Exempt Money Mika Fund \nJPMorgan \nAmato \nBank n \nVA mekoOng nano \nfor \nHe ;ova bankng buns. conducted by! P Mogan Chase a Co thrOuln ds subsdronos twandvolo mauling JPIdensan Chase &Mina:coon Trust Ccerpany. NA end J  P Morgan Snuntea Inc \nJAMS!a a mentor olio. Becomes Investor FhoSocton Ccrpreobon (SIPC). a \nnot-kr-pad \nmemorial's cosoralson funded by broxisecteasses redacted sal the Seamen and ExchangeComma:won Sowings and cosh hold fa •  customise account at \nJPIASI ore protected up 10 On amount of 550000000 The Ina $500,000 of emission. which nudges up b$100.000 of prolocton kr cosh a troweled by SIPC Te Marco ate pia•COOn linen ockeles up to an Mahone( 5900000 of praaton \nfa cash. S guided by a secants* Excess Securities Bend Sped by Treaters Casually and SuretyCompany *Minna \nThus \nSPC and excess &PC protection does \nnot \nscowl agamt bases from fluctuations in the value ante secants Assets bald in \ntt eledy by JPMCB are net meted to SIM omens \nConfidential Treatment Requested by JPMorgan JPM-SDNY-00005513 \nChase \nEFTA00014693",
    "pageCount": 9,
    "dataset": "Dataset 8"
  },
  "entities": {
    "people": [
      {
        "name": "Jeffrey Epstein",
        "role": "extracted",
        "context": "2002 \nNew York. NY 10154-1002 \nAccount Number \n• \nJEFFREY EPSTEIN \nJPMorgan Private Bank \nConfidential Page 1 of 9"
      },
      {
        "name": "Ghislaine Maxwell",
        "role": "extracted",
        "context": "RRED BY \nWIRE TO \nPALM BEACH NATL BK 8 TR CO \nFAO GHISLAINE MAXWELL \nLETTER \nFROM CLIENT \n- 5,000,000.00 \nConfidentia"
      },
      {
        "name": "Morgan Chase",
        "role": "extracted",
        "context": "09 \nJPMorgan Chase Bank \n2002 \nNew York. NY 1015"
      },
      {
        "name": "Account Number",
        "role": "extracted",
        "context": "002 \nNew York. NY 10154-1002 \nAccount Number \n• \nJEFFREY EPSTEIN \nJPMorgan"
      },
      {
        "name": "Morgan Private",
        "role": "extracted",
        "context": "Number \n• \nJEFFREY EPSTEIN \nJPMorgan Private Bank \nConfidential Page 1 of"
      },
      {
        "name": "Bank \nConfidential",
        "role": "extracted",
        "context": "REY EPSTEIN \nJPMorgan Private Bank \nConfidential Page 1 of 9 \nAsset Account \nP"
      },
      {
        "name": "Asset Account",
        "role": "extracted",
        "context": "nk \nConfidential Page 1 of 9 \nAsset Account \nPortfolio \nSeptember I - Sep"
      },
      {
        "name": "Portfolio \nSeptember",
        "role": "extracted",
        "context": "l Page 1 of 9 \nAsset Account \nPortfolio \nSeptember I - September \n30, 2002 \nTabl"
      },
      {
        "name": "Contents \nPage",
        "role": "extracted",
        "context": "September \n30, 2002 \nTable of Contents \nPage \nPortfolio Summary \n2 \nCash a"
      },
      {
        "name": "Portfolio Summary",
        "role": "extracted",
        "context": "002 \nTable of Contents \nPage \nPortfolio Summary \n2 \nCash and \nShort Term \n3"
      },
      {
        "name": "Short Term",
        "role": "extracted",
        "context": "rtfolio Summary \n2 \nCash and \nShort Term \n3 \nTrade Activity 5 \nAccount"
      },
      {
        "name": "Trade Activity",
        "role": "extracted",
        "context": "2 \nCash and \nShort Term \n3 \nTrade Activity 5 \nAccount Transactions 6 \nAc"
      },
      {
        "name": "Account Transactions",
        "role": "extracted",
        "context": "rt Term \n3 \nTrade Activity 5 \nAccount Transactions 6 \nAccount Officers \nService"
      },
      {
        "name": "Account Officers",
        "role": "extracted",
        "context": "ty 5 \nAccount Transactions 6 \nAccount Officers \nService Specialist \nRILEYIHO"
      },
      {
        "name": "Service Specialist",
        "role": "extracted",
        "context": "sactions 6 \nAccount Officers \nService Specialist \nRILEYIHORNBECKER \n000000 000"
      },
      {
        "name": "Confidential Treatment",
        "role": "extracted",
        "context": "BIT \n504 \n52 20 Cr. 330 (MN) \nConfidential Treatment Requested by JPMorgan \nChase"
      },
      {
        "name": "Morgan \nChase",
        "role": "extracted",
        "context": "tial Treatment Requested by JPMorgan \nChase \nJPM-SDNY-00005505 \nEFTA00014"
      },
      {
        "name": "Depcwt Acta",
        "role": "extracted",
        "context": "tfolio Summary \nExcept kr the Depcwt Acta\"! (e ~ir) end the osen sn pro"
      },
      {
        "name": "Mene Aceount",
        "role": "extracted",
        "context": "nformation obo& gauv JPMSP EkoMene Aceount cg the end ot the Aszet Accou"
      },
      {
        "name": "Aszet Accourd",
        "role": "extracted",
        "context": "ene Aceount cg the end ot the Aszet Accourd \n~ho \nAsset Account Portfolio"
      },
      {
        "name": "Bank \nPage",
        "role": "extracted",
        "context": "30, 2002 \nfl\nJPMorgan Private Bank \nPage 2 of 9 \nOverview \nCash & \nSho"
      },
      {
        "name": "Overview \nCash",
        "role": "extracted",
        "context": "an Private Bank \nPage 2 of 9 \nOverview \nCash & \nShort Term \nrenke( Vera 1."
      },
      {
        "name": "Accrued Income",
        "role": "extracted",
        "context": "l 6,838,687.24 14,816,643.79 \nAccrued Income 11,992 75 22,043 45 \nTotal Po"
      },
      {
        "name": "Total Portfolio",
        "role": "extracted",
        "context": "d Income 11,992 75 22,043 45 \nTotal Portfolio Value 6,850,679.99 14,838,687"
      },
      {
        "name": "Enlmetee \nAnnua",
        "role": "extracted",
        "context": "6,838,687.24 \n6,838,687.24 \nEnlmetee \nAnnua( \nincom• (,30 \n109,416.12 \n10"
      },
      {
        "name": "Asset Allocation",
        "role": "extracted",
        "context": "(,30 \n109,416.12 \n109,416.12 \nAsset Allocation \n100% Cash and Short Term \nIn"
      },
      {
        "name": "Income Summary",
        "role": "extracted",
        "context": "on \n100% Cash and Short Term \nIncome Summary \nThls Perler USD Vw to Dele U"
      },
      {
        "name": "Thls Perler",
        "role": "extracted",
        "context": "d Short Term \nIncome Summary \nThls Perler USD Vw to Dele USD` \nTaxable"
      },
      {
        "name": "Taxable Interest",
        "role": "extracted",
        "context": "s Perler USD Vw to Dele USD` \nTaxable Interest 949.99 949.99 \nU.S. Tax Exemp"
      },
      {
        "name": "Tax Exempt",
        "role": "extracted",
        "context": "Interest 949.99 949.99 \nU.S. Tax Exempt Dividends 21,093.46 \n21,475.7"
      },
      {
        "name": "Contidential Treatment",
        "role": "extracted",
        "context": "Total 22,043.45 \n22,425.73 \nContidential Treatment Requested by JPMorgan JPM-SDN"
      },
      {
        "name": "Bank \nNew",
        "role": "extracted",
        "context": "mber 30, 2002 \nJPMorgan Chase Bank \nNew York, NY 10154-1002 \nJPMorgan"
      },
      {
        "name": "Bank \nAsset",
        "role": "extracted",
        "context": "10154-1002 \nJPMorgan Private Bank \nAsset Account Portfolio Page 3 of 9"
      },
      {
        "name": "Account Portfolio",
        "role": "extracted",
        "context": "JPMorgan Private Bank \nAsset Account Portfolio Page 3 of 9 \nCash and \nShort"
      },
      {
        "name": "Maturity \nCurrent",
        "role": "extracted",
        "context": "h and \nShort Term \nSummary by Maturity \nCurrent Starner Value Estimated Annua"
      },
      {
        "name": "Starner Value",
        "role": "extracted",
        "context": "Summary by Maturity \nCurrent Starner Value Estimated Annual Income \nUSO"
      },
      {
        "name": "Estimated Annual",
        "role": "extracted",
        "context": "turity \nCurrent Starner Value Estimated Annual Income \nUSO \nUSO \nCash 957.08"
      },
      {
        "name": "Less Than",
        "role": "extracted",
        "context": "USO \nUSO \nCash 957.08 \n12.44 \nLess Than 3 Months 6,837,730.16 109,403"
      },
      {
        "name": "Type \nOescription",
        "role": "extracted",
        "context": "ture. \nCash and Short Term by Type \nOescription \nCusipSeanatoody's Rating dum"
      },
      {
        "name": "Quantify \nWarded",
        "role": "extracted",
        "context": "usipSeanatoody's Rating dummy Quantify \nWarded( \nnid \nOriginal \nMarker \nPric"
      },
      {
        "name": "Original \nMarker",
        "role": "extracted",
        "context": "dummy Quantify \nWarded( \nnid \nOriginal \nMarker \nPrice \nTax Cost \nnd \nOrigina"
      },
      {
        "name": "Price \nTax",
        "role": "extracted",
        "context": "rded( \nnid \nOriginal \nMarker \nPrice \nTax Cost \nnd \nOriginal \nCUMIN \nMa"
      },
      {
        "name": "Marker Wks",
        "role": "extracted",
        "context": "ax Cost \nnd \nOriginal \nCUMIN \nMarker Wks USD \nEstimated \nUnrearae4 \nAn"
      },
      {
        "name": "Estimated \nUnrearae",
        "role": "extracted",
        "context": "ginal \nCUMIN \nMarker Wks USD \nEstimated \nUnrearae4 \nAnnual \nON/14.055 USO Incom"
      },
      {
        "name": "Day Annualized",
        "role": "extracted",
        "context": "DEADLINE IS 11:30 AM EST) \n7-Day Annualized Yield: 1.27% \nShort Term by M"
      },
      {
        "name": "Da Annualized",
        "role": "extracted",
        "context": "LASS 11,991.92 \n(FUND 840) \n7-Da Annualized Yield: \n1.52% \nConfidential T"
      },
      {
        "name": "New \nYork",
        "role": "extracted",
        "context": "JPMorgan \nChase Bank \n2002 \nNew \nYork, \nNY 10154-1002 \n°JPMorgan Pr"
      },
      {
        "name": "Desorption \nCusip",
        "role": "extracted",
        "context": "Short Term by Type continued \nDesorption \nCusipS&P Moody's Rating \nUnir Cost"
      },
      {
        "name": "Rating \nUnir",
        "role": "extracted",
        "context": "Desorption \nCusipS&P Moody's Rating \nUnir Cost Tax Coat Covent \nEstimat"
      },
      {
        "name": "Cost Tax",
        "role": "extracted",
        "context": "CusipS&P Moody's Rating \nUnir Cost Tax Coat Covent \nEstimated Curren"
      },
      {
        "name": "Coat Covent",
        "role": "extracted",
        "context": "Moody's Rating \nUnir Cost Tax Coat Covent \nEstimated Current \nStstso'"
      },
      {
        "name": "Estimated Current",
        "role": "extracted",
        "context": "g \nUnir Cost Tax Coat Covent \nEstimated Current \nStstso' \nMania \nAtiped  \nMar"
      },
      {
        "name": "Mania \nAtiped",
        "role": "extracted",
        "context": "Estimated Current \nStstso' \nMania \nAtiped  \nMargot \nValue USO Unrealize"
      },
      {
        "name": "Margot \nValue",
        "role": "extracted",
        "context": "ent \nStstso' \nMania \nAtiped  \nMargot \nValue USO Unrealized \nAnnual Weld'"
      },
      {
        "name": "Unrealized \nAnnual",
        "role": "extracted",
        "context": "a \nAtiped  \nMargot \nValue USO Unrealized \nAnnual Weld' \nCurrency Ouantiry Orig"
      },
      {
        "name": "Currency Ouantiry",
        "role": "extracted",
        "context": "USO Unrealized \nAnnual Weld' \nCurrency Ouantiry Original Price Original Accru"
      },
      {
        "name": "Original Price",
        "role": "extracted",
        "context": "nual Weld' \nCurrency Ouantiry Original Price Original Accrued Interest USO"
      },
      {
        "name": "Original Accrued",
        "role": "extracted",
        "context": "rency Ouantiry Original Price Original Accrued Interest USO Galatoss USO Inc"
      },
      {
        "name": "Total Cash",
        "role": "extracted",
        "context": "Galatoss USO Income \nUSO WM \nTotal Cash and Short Term \nimportant Inf"
      },
      {
        "name": "Valuations \nRipen",
        "role": "extracted",
        "context": "t Information ~U. Pricing and Valuations \nRipen \nsome or went \nare \ngraded by"
      },
      {
        "name": "Realized Gain",
        "role": "extracted",
        "context": "an Private Bank \nPage 5 of 9 \nRealized Gain/Loss Summary \nShort Term Gain"
      },
      {
        "name": "Loss Summary",
        "role": "extracted",
        "context": "k \nPage 5 of 9 \nRealized Gain/Loss Summary \nShort Term Gain/Loss \nLong T"
      },
      {
        "name": "Loss \nLong",
        "role": "extracted",
        "context": "Loss Summary \nShort Term Gain/Loss \nLong Term Gain/Loss \nNote: S incic"
      },
      {
        "name": "Term Gain",
        "role": "extracted",
        "context": "y \nShort Term Gain/Loss \nLong Term Gain/Loss \nNote: S incicates Short"
      },
      {
        "name": "Loss \nNote",
        "role": "extracted",
        "context": "erm Gain/Loss \nLong Term Gain/Loss \nNote: S incicates Short Term Reali"
      },
      {
        "name": "Long Term",
        "role": "extracted",
        "context": "alized Gain/Loss \nL indicates Long Term Realized Gain/Loss \nCapital g"
      },
      {
        "name": "Loss \nCapital",
        "role": "extracted",
        "context": "cates Long Term Realized Gain/Loss \nCapital gains and losses on sales wit"
      },
      {
        "name": "Type \nTrade",
        "role": "extracted",
        "context": "0.00 \n0.00 \nTrade Activity by Type \nTrade Semement \nCare Clare Type \nOe"
      },
      {
        "name": "Semement \nCare",
        "role": "extracted",
        "context": "Trade Activity by Type \nTrade Semement \nCare Clare Type \nOeungifIon \nCurre"
      },
      {
        "name": "Clare Type",
        "role": "extracted",
        "context": "by Type \nTrade Semement \nCare Clare Type \nOeungifIon \nCurrency Quantif"
      },
      {
        "name": "Ion \nCurrency",
        "role": "extracted",
        "context": "ment \nCare Clare Type \nOeungifIon \nCurrency Quantify P/1OVUM \nName CostoP"
      },
      {
        "name": "Name Costo",
        "role": "extracted",
        "context": "n \nCurrency Quantify P/1OVUM \nName CostoProcels \nRealized \nTax \nCOW Ga"
      },
      {
        "name": "Procels \nRealized",
        "role": "extracted",
        "context": "y Quantify P/1OVUM \nName CostoProcels \nRealized \nTax \nCOW Gainless 050 \nSettl"
      },
      {
        "name": "Settled \nAug",
        "role": "extracted",
        "context": "lized \nTax \nCOW Gainless 050 \nSettled \nAug 30 Sep 3 Purchase J P MORGAN"
      },
      {
        "name": "Page Got",
        "role": "extracted",
        "context": "Bank \nAsset Account Portfolio Page Got 9 \nAccount Transactions \nCash"
      },
      {
        "name": "Cash Activity",
        "role": "extracted",
        "context": "Got 9 \nAccount Transactions \nCash Activity Summary \nAmount1MS \nPenod USD"
      },
      {
        "name": "Summary \nAmount",
        "role": "extracted",
        "context": "t Transactions \nCash Activity Summary \nAmount1MS \nPenod USD \nAmount \nYear"
      },
      {
        "name": "Amount \nYear",
        "role": "extracted",
        "context": "ummary \nAmount1MS \nPenod USD \nAmount \nYear \nto Date USD' \nBeginning Bala"
      },
      {
        "name": "Beginning Balance",
        "role": "extracted",
        "context": "Amount \nYear \nto Date USD' \nBeginning Balance \nCredits \n.00 \nDividends 21,0"
      },
      {
        "name": "Sweep Account",
        "role": "extracted",
        "context": "xable Interest 949.99 949.99 \nSweep Account Sales 48,998.65 \nSales, Matur"
      },
      {
        "name": "Miscellaneous Receipts",
        "role": "extracted",
        "context": "s 8,000,000.00 18,000,000.00 \nMiscellaneous Receipts 24,767,645.14 \nDebits \nSweep"
      },
      {
        "name": "Debits \nSweep",
        "role": "extracted",
        "context": "neous Receipts 24,767,645.14 \nDebits \nSweep Account Purchases - 957.08 \n-"
      },
      {
        "name": "Account Purchases",
        "role": "extracted",
        "context": "24,767,645.14 \nDebits \nSweep Account Purchases - 957.08 \n- \n1,339.36 \nPurcha"
      },
      {
        "name": "Miscellaneous Disbursements",
        "role": "extracted",
        "context": "- 21,086.37 - 24,837,730.16 \nMiscellaneous Disbursements - 8,000,000.00 - 18,000,000.0"
      },
      {
        "name": "Ending Balance",
        "role": "extracted",
        "context": "8,000,000.00 - 18,000,000.00 \nEnding Balance .00 \n*Year to date informatio"
      },
      {
        "name": "Date \nSettlement",
        "role": "extracted",
        "context": "ndar year basis. \nActivity by Date \nSettlement \nare Type Quantity Descnplton"
      },
      {
        "name": "Type Quantity",
        "role": "extracted",
        "context": "vity by Date \nSettlement \nare Type Quantity Descnplton Amount USD \nSep 3"
      },
      {
        "name": "Descnplton Amount",
        "role": "extracted",
        "context": "Settlement \nare Type Quantity Descnplton Amount USD \nSep 3 Dividend \nSep 3 In"
      },
      {
        "name": "Dividend \nSep",
        "role": "extracted",
        "context": "Descnplton Amount USD \nSep 3 Dividend \nSep 3 Interest \nJP MORGAN TAX FRE"
      },
      {
        "name": "Date \nSealentenz",
        "role": "extracted",
        "context": "olio Page 7 of 9 \nActivity by Date \nSealentenz \nOne \nTYPe \ncontinued \nGummy"
      },
      {
        "name": "Gummy De",
        "role": "extracted",
        "context": "entenz \nOne \nTYPe \ncontinued \nGummy DeSCOMM \nAmount \nVW \nSep 3 \nSep"
      },
      {
        "name": "Dividend \nPurchase",
        "role": "extracted",
        "context": "MM \nAmount \nVW \nSep 3 \nSep 3 \nDividend \nPurchase 21,086.37 \nJ P MORGAN TAX FRE"
      },
      {
        "name": "Morgan Chas",
        "role": "extracted",
        "context": "2002 • September 30, 2002 \nJPMorgan Chas: Bank \n2002 New York, NY 1015"
      },
      {
        "name": "Page Sof",
        "role": "extracted",
        "context": "Bank \nAsset Account Portfolio Page Sof 9 \nActivity by Date \nSealente"
      },
      {
        "name": "Date \nSealenteen",
        "role": "extracted",
        "context": "folio Page Sof 9 \nActivity by Date \nSealenteen \nOne type \ncontinued \nGummy D"
      },
      {
        "name": "Gummy Descraalon",
        "role": "extracted",
        "context": "lenteen \nOne type \ncontinued \nGummy Descraalon Amounr USD \nSep 16 Misc. \nDis"
      },
      {
        "name": "Bank \nNen",
        "role": "extracted",
        "context": "ber 30. 2002 \nJPMorgan \nChase Bank \nNen \nYork, \nNY 10154-1002 \nJPNlor"
      },
      {
        "name": "Nlorgan Private",
        "role": "extracted",
        "context": "Nen \nYork, \nNY 10154-1002 \nJPNlorgan Private Bank \nAsset Account Portfolio"
      },
      {
        "name": "In \nCase",
        "role": "extracted",
        "context": "Portfolio \nPact: C.) \nof C: \nIn \nCase of Erma or Questions About \nY"
      },
      {
        "name": "Questions About",
        "role": "extracted",
        "context": ") \nof C: \nIn \nCase of Erma or Questions About \nYour \nSabena Transfers. \nCon"
      }
    ],
    "locations": [
      {
        "name": "Palm Beach",
        "type": "location"
      },
      {
        "name": "New York, NY",
        "type": "city"
      },
      {
        "name": "New \nYork, NY",
        "type": "city"
      },
      {
        "name": "Nen \nYork, NY",
        "type": "city"
      }
    ],
    "dates": [
      {
        "date": "2002-09-30",
        "event": "September \n30, 2002"
      },
      {
        "date": "2002-09-01",
        "event": "September 01, 2002"
      },
      {
        "date": "2002-09-30",
        "event": "September 30, 2002"
      }
    ],
    "flights": [],
    "phone_numbers": [
      "000000 0000"
    ],
    "organizations": []
  },
  "processedAt": "2025-12-23T12:25:49.362Z"
}