{
  "document": {
    "id": "efta00029601",
    "filename": "EFTA00029601.pdf",
    "path": "C:\\Users\\user\\CascadeProjects\\epsteinexposed\\apps\\web\\DataSet 8\\VOL00008\\IMAGES\\0006\\EFTA00029601.pdf",
    "text": "\n\nPage 1 of 5 \nCURRICULUM VITAE \nFBI Expert Witness \nFederal Bureau of Investigation \nComputer Analysis Response Team \n26 Federal Plaza \nNew York, NY 10278 \nPHONa\nFAX: \nPROFESSIONAL EXPERIENCE \nMay 2005 - present Computer Forensic Examiner \nNew York Field Office \nFederal Bureau of Investigation \nNew York, New York \nAs a  forensic computer examiner in a  laboratory, examine physical evidence under a \ndocumented quality assurance program that includes annual proficiency testing, \ntechnical/peer and administrative reviews and adherence to standard operating \nprocedures. \nConduct forensic examinations on digital evidence and perform search and seizure \noperations. \nJan 2001— May 2005 Senior Technical Consultant \nViecore, Inc. \n1111 MacArthur Blvd. \nMahwah, NJ \nDuties included programming in many different computer languages, data base \nadministration, quality assurance management and project management. Applications \nmainly focused on Integrated Voice Response systems (IVR), web applications, and on-\nline \nbanking. \nJuly 1997 —  Jan 2001 Programmer \nErisco, Inc. \nUnion, NJ \nMaintained and coded systems to build Facets product using Pen (Both NT and UNIX \nplatforms). Served as PVCS administrator for entire Facets product. Designated build team \nleader after making significant improvements to build process. \nApril 1992 —  July 1997 Senior Environmental Health Specialist \nBergen County Health Department \nParamus, NJ \nConducted environmental investigations/inspections and hazardous materials emergency \nresponse. Coordinated enforcement efforts with NJ State Department of Environmental \nProtection. Designed and implemented entire database system utilized by Environmental \nDivision. Designed subsequent database system for Dental Health Division upon request \nof Department Director. \n3503-001 \nPage 1 of 5 \nEFTA00029601\n\nPage 2 of 5 \nEDUCATION \nJan 2015 — Dec 2019 John Jay College of Criminal Justice \nNew York, NY \nMasters in Digital Forensics and Cyber Security \nSept 1996 -  June 1998 The Chubb Institute \nParsippany. NJ \nDiploma in Computer Programming \nSept 1982 —  May 1986 Boston College \nChestnut Hill, MA \nBachelor of Science in Business and Computer Science \nFORENSIC EXAMINATION / TESTIMONY EXPERIENCE \nAnalyzed over 1000 pieces of computer media in support of over 300 cases since 2005. Participated in the \nexecution of over 200 search warrants/search and seizure operations, and field examinations. Examinations have \nsupported expert testimony in Federal Court, Southern District of NY and Eastern District of NY. \nPROFESSIONAL TRAINING \nSept 2005 Network + Certification, Northwest Regional Computer Forensic Laboratory, \nPortland, OR (5 days) \nOct 2005 Basic Data Recovery and Analysis. Intermountain West Regional Computer Forensic \nLaboratory, Salt Lake City, UT (5 days) \nNov 2005 FTK Boot Camp, Access Data, Hamilton, NJ. (3 days) \nJan 2006 A+ Certification, Intermountain West Regional Computer Forensic Laboratory, \nSalt Lake City, UT (10 days) \nFeb 2006 Advanced Windows Forensics. Rocky Mountain Regional Computer Forensic Laboratory, \nCentennial, CO (3 days) \nApril 2006 Basic Windows Certification Training Practicals, Justice Training Facility, Fredericksburg, \nVA (5 days) \nFeb 2007 Microsoft Advanced Forensics, Rocky Mountain RCFL, Denver, CO (5 days) \nJune 2007 Instructor Development Course, San Diego RCFL, San Diego, CA (5 days) \nAug 2007 RAID, FBI BWI office, Linthicum, MD (4 days) \nOct 2007 CART DES administrator, FBI BWI office, Linthicum, MD (3 days) \nDec 2007 Cell Phone/ PDA Analysis, San Diego RCFL, San Diego, CA (4 days) \nJan 2008 Access Data Internet Forensics, Rocky Mountain RCFL, Denver, CO (3 days) \nFeb 2008 Encase Intermediate Forensics, FBI Tampa Division, Tampa, FL (4 days) \nJan 2009 Microsoft Windows Vista Advanced System Forensics, Chicago, IL (3 days) \n3503-001 \nPage 2 of 5 \nEFTA00029602\n\nPage 3 of 5 \nFeb 2009 Cellebrite/Secureview Cell Phone Forensics. Salt Lake City, UT (4 days) \nApril 2009 Forward Discovery Macintosh Forensics, Menlo Park, CA (5 days) \nMay 2009 .XRY Mobile Phone Examination, Kansas City, MO (2 days) \nMarch 2010 EnCase Internet Processing, Chicago, IL (3 days) \nMarch 2010 Virtual Forensics for Linux, Denver. CO (5 days) \nAugust 2010 Live Capture, Baltimore, MD (3 days) \nDecember 2010 Forensic Tool Kit 3. Dallas, TX (3 days) \nMarch 2011 Advanced FTK Lab, Baltimore, MD (3 days) \nJune 2011 Linux Command Line. Stafford, VA (3 days) \nApril 2012 Windows 7 Artifacts, FBI BWI office, Linthicum, MD (3 days) \nSeptember 2012 FTK III for Mac, San Diego RCFL, San Diego, CA (3 days) \nMay 2014 Blacklight, NYPD Academy, New York, NY (2 days) \nMay 2014 OS Artifacts. FBI BWI office. Linthicum, MD (3 days) \nMay 2016 International Association of Computer Investigative Specialist (IACIS) Windows Forensic \nExaminer, Orlando. FL (4 days) \nMarch 2018 Cellebrite Certified Operator & Cellebrite Certified Physical Analyst, Austin, TX (5 days) \nApril 2018 Macintosh Forensics, Black Bag, San Diego. CA (5 days) \nMarch 2019 BERLA Vehicle Forensics, BERLA, Annapolis. MD (5 days) \nCERTIFICATIONS & AWARDS \nFebruary 2006 A+ Certification - CompTIA \nSeptember 2006 Net+ Certification —  CompTIA \nOctober 2006 FBI CART Basic Wintel Forensic Examiner — Federal Bureau of Investigation \nJune 2007 FBI Certified Instructor —  Federal Bureau of Investigation \nDecember 2007 PDA/Cell Phone Forensic Examiner —  Federal Bureau of Investigation \nFebruary 2008 EnCase Certification —  Federal Bureau of Investigation \nApril 2009 Macintosh Forensic Examiner —  Federal Bureau of Investigation \nAugust 2010 Senior Forensic Examiner— Federal Bureau of Investigation \nPRESENTATIONS \nSeptember 2006 FBI CART Moot Court Training, Phoenix, AZ \n3503-001 \nPage 3 of 5 \nEFTA00029603\n\nPage 4 of 5 \nAugust 2008 FBI CART Senior Moot Court Training, San Diego, CA \nOctober 2008 Instructor, ImageScan training, Bergen County Prosecutor's Office, Paramus, NJ \nJune 2009 Instructor, ImageScan training, NYPD Computer Crimes Unit, NY, NY \nJuly 2009 Instructor, ImageScan training, NYPD Computer Crimes Unit, NY. NY \nApril 2010 Infraguard Computer Forensics Show, NY, NY \nAugust 2010 Session Chair, International Conference on Cyber Security, Fordham University, NY, NY \nAugust 2010 Instructor, ImageScan training, NY, NY \nJanuary 2012 Speaker, International Conference on Cyber Security, Fordham University, NY, NY \nAugust 2013 Speaker, International Conference on Cyber Security, Fordham University, NY, NY \nJanuary 2015 Speaker, International Conference on Cyber Security, Fordham University, NY, NY \nJune 2015 Instructor, DExT Practicals Class, Stafford, VA \nJanuary 2016 Instructor, DExT Practicals Class, Stafford, VA \nAugust 2016 Speaker, International Conference on Cyber Security, Fordham University, NY, NY \nAugust 2016 Instructor, DExT Practicals Class, Stafford, VA \nOctober 2016 Instructor, DExT Practicals Class, Stafford, VA \nMarch 2017 Instructor, DExT Practicals Class, Stafford, VA \nAugust 2017 Instructor, DExT Practicals Class, Stafford, VA \nJanuary 2018 Speaker, International Conference on Cyber Security, Fordham University, NY, NY \nMarch 2018 Instructor, Digital Investigations for Prosecutors and Judges, Accra, Ghana \nSeptember 2018 \nInstructor, \nDigital Evidence and Moot Court, Accra, Ghana \nJuly 2018 Instructor, DExT Practicals Class, Linthicum, MD \nOctober 2018 Instructor, Digital Forensic Examiner I Class, Stafford, VA \nMarch 2019 Instructor, DExT Practicals Class, Linthicum, MD \nJune 2019 Instructor, Digital Forensic Examiner OS Class, Stafford, VA \nJune 2019 Instructor, Mobile Forensics and Bitcoin, Accra, Ghana \nNovember 2019 Instructor, Digital Investigations for Prosecutors, Cairo, Egypt \nAugust 2020 FBI CART Moot Court Training, Williamsburg, VA \nMarch 2021 Instructor, DExT Practicals Class, Linthicum, MD \nMay 2021 FBI CART Moot Court Training, Orlando, FL \n3503-001 \nPage 4 of 5 \nEFTA00029604\n\nPage 5 of 5 \nJune 2021 \nInstructor, Incident Response and \nAcquisition Analysis Class, \nStafford, VA \nJuly 2021 \nInstructor, DExT Practicals \nClass, Stafford, VA \n3503-001 \nPage 5 of 5 \nEFTA00029605",
    "pageCount": 5,
    "dataset": "Dataset 8"
  },
  "entities": {
    "people": [
      {
        "name": "Expert Witness",
        "role": "extracted",
        "context": "1 of 5 \nCURRICULUM VITAE \nFBI Expert Witness \nFederal Bureau of Investigat"
      },
      {
        "name": "Federal Bureau",
        "role": "extracted",
        "context": "UM VITAE \nFBI Expert Witness \nFederal Bureau of Investigation \nComputer An"
      },
      {
        "name": "Investigation \nComputer",
        "role": "extracted",
        "context": "rt Witness \nFederal Bureau of Investigation \nComputer Analysis Response Team \n26 Fe"
      },
      {
        "name": "Analysis Response",
        "role": "extracted",
        "context": "au of Investigation \nComputer Analysis Response Team \n26 Federal Plaza \nNew Y"
      },
      {
        "name": "Federal Plaza",
        "role": "extracted",
        "context": "er Analysis Response Team \n26 Federal Plaza \nNew York, NY 10278 \nPHONa\nFA"
      },
      {
        "name": "Computer Forensic",
        "role": "extracted",
        "context": "XPERIENCE \nMay 2005 - present Computer Forensic Examiner \nNew York Field Offi"
      },
      {
        "name": "Examiner \nNew",
        "role": "extracted",
        "context": "5 - present Computer Forensic Examiner \nNew York Field Office \nFederal Bu"
      },
      {
        "name": "York Field",
        "role": "extracted",
        "context": "mputer Forensic Examiner \nNew York Field Office \nFederal Bureau of Inv"
      },
      {
        "name": "Office \nFederal",
        "role": "extracted",
        "context": "nsic Examiner \nNew York Field Office \nFederal Bureau of Investigation \nNew"
      },
      {
        "name": "Investigation \nNew",
        "role": "extracted",
        "context": "eld Office \nFederal Bureau of Investigation \nNew York, New York \nAs a  forensi"
      },
      {
        "name": "Senior Technical",
        "role": "extracted",
        "context": "erations. \nJan 2001— May 2005 Senior Technical Consultant \nViecore, Inc. \n11"
      },
      {
        "name": "Consultant \nViecore",
        "role": "extracted",
        "context": "01— May 2005 Senior Technical Consultant \nViecore, Inc. \n1111 MacArthur Blvd."
      },
      {
        "name": "Arthur Blvd",
        "role": "extracted",
        "context": "ltant \nViecore, Inc. \n1111 MacArthur Blvd. \nMahwah, NJ \nDuties included"
      },
      {
        "name": "Integrated Voice",
        "role": "extracted",
        "context": "plications \nmainly focused on Integrated Voice Response systems (IVR), web a"
      },
      {
        "name": "Programmer \nErisco",
        "role": "extracted",
        "context": "nking. \nJuly 1997 —  Jan 2001 Programmer \nErisco, Inc. \nUnion, NJ \nMaintained"
      },
      {
        "name": "Senior Environmental",
        "role": "extracted",
        "context": "ess. \nApril 1992 —  July 1997 Senior Environmental Health Specialist \nBergen Cou"
      },
      {
        "name": "Health Specialist",
        "role": "extracted",
        "context": "uly 1997 Senior Environmental Health Specialist \nBergen County Health Departm"
      },
      {
        "name": "Bergen County",
        "role": "extracted",
        "context": "ironmental Health Specialist \nBergen County Health Department \nParamus, N"
      },
      {
        "name": "Health Department",
        "role": "extracted",
        "context": "lth Specialist \nBergen County Health Department \nParamus, NJ \nConducted envir"
      },
      {
        "name": "State Department",
        "role": "extracted",
        "context": "d enforcement efforts with NJ State Department of Environmental \nProtection."
      },
      {
        "name": "Environmental \nProtection",
        "role": "extracted",
        "context": "s with NJ State Department of Environmental \nProtection. Designed and implemented ent"
      },
      {
        "name": "Environmental \nDivision",
        "role": "extracted",
        "context": "e database system utilized by Environmental \nDivision. Designed subsequent database"
      },
      {
        "name": "Dental Health",
        "role": "extracted",
        "context": "ubsequent database system for Dental Health Division upon request \nof Dep"
      },
      {
        "name": "Department Director",
        "role": "extracted",
        "context": "lth Division upon request \nof Department Director. \n3503-001 \nPage 1 of 5 \nEFTA"
      },
      {
        "name": "John Jay",
        "role": "extracted",
        "context": "DUCATION \nJan 2015 — Dec 2019 John Jay College of Criminal Justice"
      },
      {
        "name": "Criminal Justice",
        "role": "extracted",
        "context": "Dec 2019 John Jay College of Criminal Justice \nNew York, NY \nMasters in Dig"
      },
      {
        "name": "Digital Forensics",
        "role": "extracted",
        "context": "ice \nNew York, NY \nMasters in Digital Forensics and Cyber Security \nSept 1996"
      },
      {
        "name": "Cyber Security",
        "role": "extracted",
        "context": "ters in Digital Forensics and Cyber Security \nSept 1996 -  June 1998 The C"
      },
      {
        "name": "The Chubb",
        "role": "extracted",
        "context": "urity \nSept 1996 -  June 1998 The Chubb Institute \nParsippany. NJ \nDi"
      },
      {
        "name": "Institute \nParsippany",
        "role": "extracted",
        "context": "t 1996 -  June 1998 The Chubb Institute \nParsippany. NJ \nDiploma in Computer Prog"
      },
      {
        "name": "Computer Programming",
        "role": "extracted",
        "context": "e \nParsippany. NJ \nDiploma in Computer Programming \nSept 1982 —  May 1986 Boston"
      },
      {
        "name": "Boston College",
        "role": "extracted",
        "context": "amming \nSept 1982 —  May 1986 Boston College \nChestnut Hill, MA \nBachelor"
      },
      {
        "name": "Chestnut Hill",
        "role": "extracted",
        "context": "2 —  May 1986 Boston College \nChestnut Hill, MA \nBachelor of Science in B"
      },
      {
        "name": "Computer Science",
        "role": "extracted",
        "context": "or of Science in Business and Computer Science \nFORENSIC EXAMINATION / TESTI"
      },
      {
        "name": "Federal Court",
        "role": "extracted",
        "context": "supported expert testimony in Federal Court, Southern District of NY and"
      },
      {
        "name": "Southern District",
        "role": "extracted",
        "context": "t testimony in Federal Court, Southern District of NY and Eastern District of"
      },
      {
        "name": "Eastern District",
        "role": "extracted",
        "context": ", Southern District of NY and Eastern District of NY. \nPROFESSIONAL TRAINING"
      },
      {
        "name": "Northwest Regional",
        "role": "extracted",
        "context": "2005 Network + Certification, Northwest Regional Computer Forensic Laboratory,"
      },
      {
        "name": "Basic Data",
        "role": "extracted",
        "context": "rtland, OR (5 days) \nOct 2005 Basic Data Recovery and Analysis. Interm"
      },
      {
        "name": "Intermountain West",
        "role": "extracted",
        "context": "c Data Recovery and Analysis. Intermountain West Regional Computer Forensic \nL"
      },
      {
        "name": "Regional Computer",
        "role": "extracted",
        "context": "Analysis. Intermountain West Regional Computer Forensic \nLaboratory, Salt La"
      },
      {
        "name": "Forensic \nLaboratory",
        "role": "extracted",
        "context": "untain West Regional Computer Forensic \nLaboratory, Salt Lake City, UT (5 days)"
      },
      {
        "name": "Salt Lake",
        "role": "extracted",
        "context": "omputer Forensic \nLaboratory, Salt Lake City, UT (5 days) \nNov 2005 F"
      },
      {
        "name": "Boot Camp",
        "role": "extracted",
        "context": "ty, UT (5 days) \nNov 2005 FTK Boot Camp, Access Data, Hamilton, NJ. ("
      },
      {
        "name": "Access Data",
        "role": "extracted",
        "context": "ays) \nNov 2005 FTK Boot Camp, Access Data, Hamilton, NJ. (3 days) \nJan"
      },
      {
        "name": "Forensic Laboratory",
        "role": "extracted",
        "context": "untain West Regional Computer Forensic Laboratory, \nSalt Lake City, UT (10 days"
      },
      {
        "name": "Advanced Windows",
        "role": "extracted",
        "context": "City, UT (10 days) \nFeb 2006 Advanced Windows Forensics. Rocky Mountain Reg"
      },
      {
        "name": "Rocky Mountain",
        "role": "extracted",
        "context": "6 Advanced Windows Forensics. Rocky Mountain Regional Computer Forensic La"
      },
      {
        "name": "Basic Windows",
        "role": "extracted",
        "context": "nial, CO (3 days) \nApril 2006 Basic Windows Certification Training Practi"
      },
      {
        "name": "Certification Training",
        "role": "extracted",
        "context": "ys) \nApril 2006 Basic Windows Certification Training Practicals, Justice Training"
      },
      {
        "name": "Justice Training",
        "role": "extracted",
        "context": "fication Training Practicals, Justice Training Facility, Fredericksburg, \nVA"
      },
      {
        "name": "Microsoft Advanced",
        "role": "extracted",
        "context": "sburg, \nVA (5 days) \nFeb 2007 Microsoft Advanced Forensics, Rocky Mountain RCF"
      },
      {
        "name": "Instructor Development",
        "role": "extracted",
        "context": "enver, CO (5 days) \nJune 2007 Instructor Development Course, San Diego RCFL, San D"
      },
      {
        "name": "San Diego",
        "role": "extracted",
        "context": "nstructor Development Course, San Diego RCFL, San Diego, CA (5 days)"
      },
      {
        "name": "Cell Phone",
        "role": "extracted",
        "context": "thicum, MD (3 days) \nDec 2007 Cell Phone/ PDA Analysis, San Diego RCFL"
      },
      {
        "name": "Internet Forensics",
        "role": "extracted",
        "context": "4 days) \nJan 2008 Access Data Internet Forensics, Rocky Mountain RCFL, Denver,"
      },
      {
        "name": "Encase Intermediate",
        "role": "extracted",
        "context": "Denver, CO (3 days) \nFeb 2008 Encase Intermediate Forensics, FBI Tampa Division"
      },
      {
        "name": "Tampa Division",
        "role": "extracted",
        "context": "e Intermediate Forensics, FBI Tampa Division, Tampa, FL (4 days) \nJan 2009"
      },
      {
        "name": "Microsoft Windows",
        "role": "extracted",
        "context": "Tampa, FL (4 days) \nJan 2009 Microsoft Windows Vista Advanced System Forensi"
      },
      {
        "name": "Vista Advanced",
        "role": "extracted",
        "context": ") \nJan 2009 Microsoft Windows Vista Advanced System Forensics, Chicago, IL"
      },
      {
        "name": "System Forensics",
        "role": "extracted",
        "context": "rosoft Windows Vista Advanced System Forensics, Chicago, IL (3 days) \n3503-0"
      },
      {
        "name": "Secureview Cell",
        "role": "extracted",
        "context": "e 3 of 5 \nFeb 2009 Cellebrite/Secureview Cell Phone Forensics. Salt Lake Ci"
      },
      {
        "name": "Phone Forensics",
        "role": "extracted",
        "context": "09 Cellebrite/Secureview Cell Phone Forensics. Salt Lake City, UT (4 days)"
      },
      {
        "name": "Forward Discovery",
        "role": "extracted",
        "context": "City, UT (4 days) \nApril 2009 Forward Discovery Macintosh Forensics, Menlo Pa"
      },
      {
        "name": "Macintosh Forensics",
        "role": "extracted",
        "context": "April 2009 Forward Discovery Macintosh Forensics, Menlo Park, CA (5 days) \nMay"
      },
      {
        "name": "Menlo Park",
        "role": "extracted",
        "context": "iscovery Macintosh Forensics, Menlo Park, CA (5 days) \nMay 2009 .XRY M"
      },
      {
        "name": "Mobile Phone",
        "role": "extracted",
        "context": "k, CA (5 days) \nMay 2009 .XRY Mobile Phone Examination, Kansas City, MO"
      },
      {
        "name": "Kansas City",
        "role": "extracted",
        "context": "XRY Mobile Phone Examination, Kansas City, MO (2 days) \nMarch 2010 EnCa"
      },
      {
        "name": "Case Internet",
        "role": "extracted",
        "context": "ty, MO (2 days) \nMarch 2010 EnCase Internet Processing, Chicago, IL (3 da"
      },
      {
        "name": "Virtual Forensics",
        "role": "extracted",
        "context": "cago, IL (3 days) \nMarch 2010 Virtual Forensics for Linux, Denver. CO (5 days"
      },
      {
        "name": "Live Capture",
        "role": "extracted",
        "context": "ver. CO (5 days) \nAugust 2010 Live Capture, Baltimore, MD (3 days) \nDece"
      },
      {
        "name": "Forensic Tool",
        "role": "extracted",
        "context": "e, MD (3 days) \nDecember 2010 Forensic Tool Kit 3. Dallas, TX (3 days) \nM"
      },
      {
        "name": "Linux Command",
        "role": "extracted",
        "context": "imore, MD (3 days) \nJune 2011 Linux Command Line. Stafford, VA (3 days)"
      },
      {
        "name": "International Association",
        "role": "extracted",
        "context": "thicum, MD (3 days) \nMay 2016 International Association of Computer Investigative Spe"
      },
      {
        "name": "Computer Investigative",
        "role": "extracted",
        "context": "International Association of Computer Investigative Specialist (IACIS) Windows Fo"
      },
      {
        "name": "Windows Forensic",
        "role": "extracted",
        "context": "estigative Specialist (IACIS) Windows Forensic \nExaminer, Orlando. FL (4 day"
      },
      {
        "name": "Cellebrite Certified",
        "role": "extracted",
        "context": "ando. FL (4 days) \nMarch 2018 Cellebrite Certified Operator & Cellebrite Certifi"
      },
      {
        "name": "Physical Analyst",
        "role": "extracted",
        "context": "erator & Cellebrite Certified Physical Analyst, Austin, TX (5 days) \nApril 2"
      },
      {
        "name": "Black Bag",
        "role": "extracted",
        "context": "ril 2018 Macintosh Forensics, Black Bag, San Diego. CA (5 days) \nMarc"
      },
      {
        "name": "Vehicle Forensics",
        "role": "extracted",
        "context": "CA (5 days) \nMarch 2019 BERLA Vehicle Forensics, BERLA, Annapolis. MD (5 days"
      },
      {
        "name": "Basic Wintel",
        "role": "extracted",
        "context": "ompTIA \nOctober 2006 FBI CART Basic Wintel Forensic Examiner — Federal B"
      },
      {
        "name": "Forensic Examiner",
        "role": "extracted",
        "context": "er 2006 FBI CART Basic Wintel Forensic Examiner — Federal Bureau of Investiga"
      },
      {
        "name": "Investigation \nJune",
        "role": "extracted",
        "context": "Examiner — Federal Bureau of Investigation \nJune 2007 FBI Certified Instructor"
      },
      {
        "name": "Certified Instructor",
        "role": "extracted",
        "context": "Investigation \nJune 2007 FBI Certified Instructor —  Federal Bureau of Investig"
      },
      {
        "name": "Investigation \nDecember",
        "role": "extracted",
        "context": "structor —  Federal Bureau of Investigation \nDecember 2007 PDA/Cell Phone Forensic"
      },
      {
        "name": "Investigation \nFebruary",
        "role": "extracted",
        "context": "Examiner —  Federal Bureau of Investigation \nFebruary 2008 EnCase Certification —"
      },
      {
        "name": "Case Certification",
        "role": "extracted",
        "context": "nvestigation \nFebruary 2008 EnCase Certification —  Federal Bureau of Investig"
      },
      {
        "name": "Investigation \nApril",
        "role": "extracted",
        "context": "fication —  Federal Bureau of Investigation \nApril 2009 Macintosh Forensic Exami"
      },
      {
        "name": "Macintosh Forensic",
        "role": "extracted",
        "context": "of Investigation \nApril 2009 Macintosh Forensic Examiner —  Federal Bureau of"
      },
      {
        "name": "Investigation \nAugust",
        "role": "extracted",
        "context": "Examiner —  Federal Bureau of Investigation \nAugust 2010 Senior Forensic Examiner"
      },
      {
        "name": "Senior Forensic",
        "role": "extracted",
        "context": "of Investigation \nAugust 2010 Senior Forensic Examiner— Federal Bureau of I"
      },
      {
        "name": "Moot Court",
        "role": "extracted",
        "context": "IONS \nSeptember 2006 FBI CART Moot Court Training, Phoenix, AZ \n3503-0"
      },
      {
        "name": "Senior Moot",
        "role": "extracted",
        "context": "4 of 5 \nAugust 2008 FBI CART Senior Moot Court Training, San Diego, CA"
      },
      {
        "name": "Court Training",
        "role": "extracted",
        "context": "ust 2008 FBI CART Senior Moot Court Training, San Diego, CA \nOctober 2008"
      },
      {
        "name": "Computer Crimes",
        "role": "extracted",
        "context": "tor, ImageScan training, NYPD Computer Crimes Unit, NY, NY \nJuly 2009 Instr"
      },
      {
        "name": "Infraguard Computer",
        "role": "extracted",
        "context": "imes Unit, NY. NY \nApril 2010 Infraguard Computer Forensics Show, NY, NY \nAugus"
      },
      {
        "name": "Forensics Show",
        "role": "extracted",
        "context": "pril 2010 Infraguard Computer Forensics Show, NY, NY \nAugust 2010 Session"
      },
      {
        "name": "Session Chair",
        "role": "extracted",
        "context": "ics Show, NY, NY \nAugust 2010 Session Chair, International Conference on"
      },
      {
        "name": "International Conference",
        "role": "extracted",
        "context": "Y \nAugust 2010 Session Chair, International Conference on Cyber Security, Fordham Un"
      },
      {
        "name": "Fordham University",
        "role": "extracted",
        "context": "Conference on Cyber Security, Fordham University, NY, NY \nAugust 2010 Instruct"
      }
    ],
    "locations": [
      {
        "name": "New York, NY",
        "type": "city"
      },
      {
        "name": "Mahwah, NJ",
        "type": "city"
      },
      {
        "name": "Union, NJ",
        "type": "city"
      },
      {
        "name": "Department \nParamus, NJ",
        "type": "city"
      },
      {
        "name": "Chestnut Hill, MA",
        "type": "city"
      },
      {
        "name": "Portland, OR",
        "type": "city"
      },
      {
        "name": "Lake City, UT",
        "type": "city"
      },
      {
        "name": "Hamilton, NJ",
        "type": "city"
      },
      {
        "name": "Centennial, CO",
        "type": "city"
      },
      {
        "name": "Fredericksburg, VA",
        "type": "city"
      },
      {
        "name": "Denver, CO",
        "type": "city"
      },
      {
        "name": "San Diego, CA",
        "type": "city"
      },
      {
        "name": "Linthicum, MD",
        "type": "city"
      },
      {
        "name": "Tampa, FL",
        "type": "city"
      },
      {
        "name": "Chicago, IL",
        "type": "city"
      },
      {
        "name": "Menlo Park, CA",
        "type": "city"
      },
      {
        "name": "Kansas City, MO",
        "type": "city"
      },
      {
        "name": "Baltimore, MD",
        "type": "city"
      },
      {
        "name": "Dallas, TX",
        "type": "city"
      },
      {
        "name": "Stafford, VA",
        "type": "city"
      },
      {
        "name": "Austin, TX",
        "type": "city"
      },
      {
        "name": "Phoenix, AZ",
        "type": "city"
      },
      {
        "name": "Paramus, NJ",
        "type": "city"
      },
      {
        "name": "Crimes Unit, NY",
        "type": "city"
      },
      {
        "name": "Forensics Show, NY",
        "type": "city"
      },
      {
        "name": "Fordham University, NY",
        "type": "city"
      },
      {
        "name": "Williamsburg, VA",
        "type": "city"
      },
      {
        "name": "Orlando, FL",
        "type": "city"
      }
    ],
    "dates": [
      {
        "date": "2008-08-05",
        "event": "5 \nAugust 2008"
      },
      {
        "date": "2021-06-05",
        "event": "5 \nJune 2021"
      }
    ],
    "flights": [],
    "phone_numbers": [],
    "organizations": []
  },
  "processedAt": "2025-12-23T12:26:23.775Z"
}